Workbook

Sheet Loan_Data
A1: Loan_ID | B1: Customer_Name | C1: Age | D1: Gender | E1: County | F1: Employment_Status | G1: Employment_Length_Years | H1: Annual_Income_KES | I1: Loan_Amount_KES | J1: Interest_Rate_Percent | K1: Loan_Term_Months | L1: Loan_Purpose | M1: Credit_Score | N1: Num_Late_Payments | O1: Loan_Status | P1: Issue_Date | Q1: Debt_To_Income_Ratio
A2: LN-00202 | B2: Carl West | C2: 3 | D2: Male | E2: Nakuru | F2: Business Owner | G2: 7 | H2: 1777690 | I2: 49336 | J2: 11.45 | K2: 48 | L2: Medical | M2: 417 | N2: 4 | O2: Late (31-60 days) | P2: 2020-12-04 | Q2: 0.0278 | T2: Median Age
A3: LN-00686 | B3: Misty Anderson | C3: 42 | D3: Male | E3: Kisumu | F3: Employed | G3: 11 | H3: 1608080 | I3: 639064 | J3: 12.18 | K3: 12 | L3: Personal | M3: 303 | N3: 0 | O3: Fully Paid | P3: 2022-05-08 | Q3: 0.3974
A4: LN-01423 | B4: Albert Bailey | C4: 59 | D4: FEMALE | E4: Machakos | G4: 26 | H4: 1342189 | I4: 694174 | J4: 25.16 | K4: 36 | L4: Medical | M4: 676 | N4: 1 | O4: Fully Paid | P4: 2023-11-05 | Q4: 0.5172
A5: LN-01136 | B5: Emily Barnes | C5: 21 | D5: Female | E5: Kisumu | F5: Self-Employed | G5: 15 | H5: 645982 | I5: 104811 | J5: 22.48 | K5: 24 | M5: 591 | N5: 6 | O5: Late (31-60 days) | P5: 2021-01-25 | Q5: 0.1623
A6: LN-00479 | B6: Troy Carrillo IV | C6: 21 | D6: Female | E6: Thika | F6: Self-Employed | G6: 11 | H6: -1386861 | I6: 667096 | J6: 19.51 | K6: 12 | L6: Home Improvement | M6: 786 | N6: 0 | O6: Current | P6: 31 Jul 2022 | Q6: 0.481
A7: LN-00680 | B7: Gerald Mason | C7: 38 | D7: Female | E7: Kakamega | F7: Business Owner | G7: 28 | H7: 2036231 | I7: 567219 | J7: 16.03 | K7: 60 | L7: Medical | M7: 820 | N7: 2 | O7: Fully Paid | P7: 2022-02-18 | Q7: 0.2786
A8: LN-01257 | B8: George Bass | C8: 41 | D8: Male | E8: Nakuru | F8: Employed | G8: 27 | H8: 1266787 | I8: 614302 | J8: 14.85 | K8: 36 | L8: Business | M8: 441 | N8: 3 | O8: Current | P8: 2021-04-20 | Q8: 0.4849
A9: LN-00161 | B9: Tyler Gillespie | C9: 8 | D9: Female | E9: Machakos | F9: Self-Employed | G9: 4 | H9: 2061175 | I9: 153172 | J9: 14.84 | K9: 24 | L9: Medical | M9: 402 | N9: 5 | O9: Current | P9: 2020-11-19 | Q9: 0.0743
A10: LN-00499 | B10: Robert Randall | C10: 54 | D10: Male | E10: Thika | F10: Self-Employed | G10: 27 | H10: 874892 | I10: 733087 | J10: 17.31 | K10: 60 | L10: Medical | M10: 766 | N10: 7 | O10: Charged Off | P10: 2020-02-26 | Q10: 0.8379
A11: LN-01250 | B11: Nancy Fields | C11: 49 | D11: Male | E11: Kakamega | F11: Unemployed | G11: 16 | H11: 827341 | I11: 798754 | J11: 26.96 | K11: 24 | L11: Agriculture | M11: 840 | N11: 3 | O11: Fully Paid | P11: 2022-02-22 | Q11: 0.9654
A12: LN-01413 | B12: Paul Williams | C12: 55 | D12: Male | E12: Nyeri | F12: Business Owner | G12: 24 | H12: 1596953 | I12: 523323 | J12: 16.61 | K12: 48 | L12: Medical | M12: 644 | N12: 5 | O12: Late (31-60 days) | P12: 2021-07-26 | Q12: 0.3277
A13: LN-00087 | B13: Michael Mckee | C13: 21 | D13: Male | E13: Kisumu | F13: Unemployed | G13: 11 | H13: 1141568 | I13: 118538 | J13: 12.74 | K13: 60 | M13: 306 | N13: 1 | O13: Fully Paid | P13: 2023-07-24 | Q13: 0.1038
A14: LN-01498 | B14: Ashley Stout | C14: 48 | D14: Male | E14: Nairobi | F14: Employed | G14: 23 | H14: 2043462 | I14: 546169 | J14: 8.9 | K14: 60 | L14: Home Improvement | M14: 785 | N14: 3 | O14: Late (61-90 days) | P14: 2020-05-04 | Q14: 0.2673
A15: LN-00308 | B15: Meagan Fernandez | C15: 47 | D15: Male | E15: Mombasa | F15: Self-Employed | G15: 20 | H15: 1387068 | I15: 128042 | J15: 24.88 | K15: 60 | L15: Personal | M15: 813 | N15: 7 | O15: Default | P15: 2022-05-16 | Q15: 0.0923
A16: LN-00663 | B16: Kelly Gomez | C16: 53 | D16: Female | E16: Nyeri | F16: Employed | G16: 2 | H16: 1865996 | I16: 626226 | J16: 16.01 | K16: 36 | L16: Home Improvement | M16: 609 | N16: 2 | O16: Charged Off | P16: 2023-12-17 | Q16: 0.3356
A17: LN-00019 | B17: Shawn Wong DDS | C17: 44 | D17: Male | E17: Thika | F17: Self-Employed | G17: 15 | H17: 2165209 | I17: 687505 | J17: 9.74 | K17: 24 | L17: Medical | M17: 436 | N17: 3 | O17: Late (31-60 days) | P17: 2022-10-31 | Q17: 0.3175
A18: LN-00723 | B18: Casey Hall | C18: 59 | D18: Female | E18: Eldoret | F18: Unemployed | G18: 21 | H18: 809085 | I18: 50949 | J18: 18.33 | K18: 24 | L18: Medical | M18: 302 | N18: 0 | O18: Fully Paid | P18: 2021-03-09 | Q18: 0.063
A19: LN-01231 | B19: Terri Kim | C19: 44 | D19: Female | E19: Machakos | F19: Business Owner | G19: 19 | H19: 1823312 | I19: 221202 | J19: 11.35 | K19: 36 | L19: Education | M19: 488 | N19: 3 | O19: Late (61-90 days) | P19: 2020-02-29 | Q19: 0.1213
A20: LN-00142 | B20: Jennifer Booker | C20: 24 | D20: Female | E20: Thika | F20: Unemployed | G20: 9 | H20: 259083 | I20: 329521 | J20: 23.08 | K20: 24 | L20: Agriculture | M20: 680 | N20: 7 | O20: Current | P20: 2020-05-10 | Q20: 1.2719
A21: LN-00454 | B21: Jamie Savage | C21: 54 | D21: Male | E21: Nakuru | F21: Unemployed | G21: 16 | H21: 741672 | I21: 245391 | J21: 26.69 | K21: 48 | L21: Medical | M21: 552 | N21: 1 | O21: Fully Paid | P21: 2020-07-29 | Q21: 0.3309
A22: LN-01192 | B22: Tiffany Chavez | C22: 36 | D22: Male | E22: Meru | F22: Unemployed | G22: 18 | H22: 1730184 | I22: 176255 | J22: 17.86 | K22: 48 | L22: Business | M22: 422 | N22: 4 | O22: Charged Off | P22: 2020-10-22 | Q22: 0.1019
A23: LN-00330 | B23: Randy Williams | C23: 51 | D23: Male | E23: Nakuru | F23: Business Owner | G23: 1 | H23: 2228891 | I23: 733987 | J23: 20.07 | K23: 60 | L23: Agriculture | M23: 365 | N23: 4 | O23: Fully Paid | P23: 2022-11-06 | Q23: 0.3293
A24: LN-01355 | B24: Michael Herrera | C24: 45 | D24: Female | E24: Eldoret | F24: Employed | G24: 1 | H24: 2152424 | I24: 125686 | J24: 9.03 | K24: 48 | L24: Agriculture | M24: 472 | N24: 3 | O24: Late (61-90 days) | P24: 2022-03-19 | Q24: 0.0584
B25: Leslie Rich | C25: 23 | D25: Female | E25: Thika | F25: Employed | G25: 1 | H25: 368490 | I25: 287247 | J25: 19.07 | K25: 24 | L25: Home Improvement | M25: 403 | N25: 5 | O25: fully paid | P25: 2021-10-08 | Q25: 0.7795
A26: LN-00739 | B26: Robert Sellers MD | C26: 22 | D26: Male | E26: Nakuru | F26: Business Owner | G26: 20 | H26: 1123693 | I26: 393216 | J26: 9.09 | K26: 12 | L26: Business | M26: 498 | N26: 3 | O26: Late (31-60 days) | P26: 2020-05-20 | Q26: 0.3499
A27: LN-00492 | B27: Mark Guerrero | C27: 37 | E27: Nairobi | F27: Self-Employed | G27: 6 | H27: 373510 | I27: 241883 | J27: 24.99 | K27: 24 | L27: Home Improvement | M27: 804 | N27: 2 | O27: Charged Off | P27: 2021-12-20 | Q27: 0.6476
A28: LN-00656 | B28: Austin Joyce | C28: 48 | D28: Male | E28: Kisumu | F28: Unemployed | G28: 14 | H28: 1859161 | I28: 174692 | J28: 14.79 | K28: 60 | L28: Medical | M28: 552 | N28: 5 | O28: Late (31-60 days) | P28: 2020-06-14 | Q28: 0.094
A29: LN-01429 | B29: Sandra Johnson | C29: 30 | D29: Female | E29: Mombasa | F29: Business Owner | G29: 2 | H29: 305438 | I29: 589354 | J29: 18.55 | K29: 60 | L29: Home Improvement | M29: 328 | N29: 6 | O29: Default | P29: 2022-03-26 | Q29: 1.9295
A30: LN-00309 | B30: Brenda Pitts | C30: 54 | D30: Female | E30: Nakuru | F30: Business Owner | G30: 25 | H30: 1702688 | I30: 74110 | J30: 17.68 | K30: 60 | L30: Agriculture | M30: 802 | N30: 6 | O30: Charged Off | P30: 2023-11-27 | Q30: 0.0435
A31: LN-00938 | B31: Christian Douglas | C31: 22 | D31: Female | E31: Machakos | F31: Employed | G31: 1 | H31: 1636081 | I31: 210920 | J31: 19.1 | K31: 24 | L31: Agriculture | M31: 809 | N31: 5 | O31: Charged Off | P31: 2023-11-06 | Q31: 0.1289
A32: LN-00288 | B32: Janet Johnson | C32: 56 | D32: Female | E32: Machakos | F32: Employed | G32: 18 | H32: 1103780 | I32: 515164 | J32: 25.72 | K32: 36 | L32: Home Improvement | M32: 464 | N32: 4 | O32: Fully Paid | P32: 2020-04-13 | Q32: 0.4667
A33: LN-01415 | B33: Samuel Smith | C33: 54 | D33: Male | E33: Meru | F33: Employed | G33: 3 | H33: 601280 | I33: 797635 | J33: 22.13 | K33: 24 | L33: Agriculture | M33: 849 | N33: 2 | O33: Default | P33: 11-14-2023 | Q33: 1.3266
A34: LN-00468 | B34: Joseph Cortez MD | C34: 47 | D34: Female | E34: Thika | F34: Employed | G34: 17 | H34: 691083 | I34: 396087 | J34: 25.31 | K34: 12 | L34: Agriculture | M34: 449 | N34: 6 | O34: Late (61-90 days) | P34: 2023-10-03 | Q34: 0.5731
A35: LN-00448 | B35: Richard Gonzalez | C35: 50 | D35: Female | E35: Nairobi | F35: Business Owner | G35: 6 | H35: 746956 | I35: 407699 | J35: 16.22 | K35: 12 | L35: Agriculture | M35: 725 | N35: 6 | O35: current | P35: 2020-03-22 | Q35: 0.5458
A36: LN-01117 | B36: Steven Hernandez | C36: 27 | D36: Male | E36: Nairobi | F36: Employed | G36: 28 | H36: 656513 | I36: 83972 | J36: 23.04 | K36: 48 | L36: Business | M36: 681 | N36: 6 | O36: Default | P36: 2021-04-05 | Q36: 0.1279
A37: LN-01028 | B37: Scott Pham | C37: 58 | D37: Female | E37: Machakos | F37: Business Owner | G37: 11 | H37: -551616 | I37: 686015 | J37: 26.9 | K37: 48 | L37: Home Improvement | M37: 628 | N37: 1 | O37: Charged Off | P37: 2023-05-09 | Q37: 1.2436
A38: LN-00637 | B38: Matthew Salazar | C38: 23 | D38: Female | E38: Nyeri | F38: Employed | G38: 5 | H38: 1724613 | I38: 425105 | J38: 26.23 | K38: 12 | L38: Business | M38: 596 | N38: 7 | O38: Late (31-60 days) | P38: 2022-08-30 | Q38: 0.2465
A39: LN-00075 | B39: Susan Taylor | C39: 34 | D39: male | E39: Kakamega | F39: Employed | G39: 14 | H39: 777897 | I39: 411858 | J39: 8.99 | K39: 24 | L39: Home Improvement | M39: 552 | N39: 2 | O39: Current | P39: 2022-01-17 | Q39: 0.5295
A40: LN-01481 | B40: Megan Franklin | C40: 38 | D40: Female | E40: Mombasa | F40: Business Owner | G40: 10 | H40: 2287359 | I40: 550875 | J40: 12.73 | K40: 36 | L40: Personal | M40: 714 | N40: 6 | O40: Late (31-60 days) | P40: 2022-09-02 | Q40: 0.2408
A41: LN-00043 | B41: Timothy Jacobson | C41: 24 | D41: Male | E41: Mombasa | F41: Unemployed | G41: 16 | H41: 228874 | I41: 289160 | J41: 12.15 | K41: 36 | M41: 460 | N41: 5 | O41: Late (61-90 days) | P41: 2022-02-17 | Q41: 1.2634
A42: LN-00261 | B42: Jessica Ramsey | C42: 29 | D42: Male | E42: Kisumu | F42: Business Owner | G42: 20 | H42: 1437949 | I42: 400596 | J42: 19.01 | K42: 48 | L42: Agriculture | M42: 652 | N42: 7 | O42: Default | P42: 2022-05-17 | Q42: 0.2786
A43: LN-00058 | B43: Jade Miles | C43: 60 | D43: Male | E43: Eldoret | F43: Business Owner | G43: 0 | H43: 1396959 | I43: 388266 | J43: 8.61 | K43: 48 | L43: Education | M43: 691 | N43: 4 | O43: Default | P43: 2023-06-20 | Q43: 0.2779
A44: LN-00982 | B44: Crystal Ramos | C44: 38 | D44: Male | E44: Kisumu | F44: Self-Employed | G44: 10 | H44: 1277353 | I44: 35534 | J44: 27.53 | K44: 36 | L44: Home Improvement | M44: 388 | N44: 7 | O44: Default | P44: 2023-05-01 | Q44: 0.0278
A45: LN-00603 | B45: Amanda Smith | C45: 59 | E45: Nyeri | F45: Self-Employed | G45: 2 | H45: 1710891 | I45: 492963 | J45: 20.34 | K45: 60 | L45: Agriculture | M45: 477 | N45: 5 | O45: Fully Paid | P45: 2022-02-25 | Q45: 0.2881
A46: LN-00839 | B46: Thomas Willis | C46: 45 | D46: Male | E46: Eldoret | F46: Business Owner | G46: 11 | H46: 1762460 | I46: 718876 | J46: 13.61 | K46: 36 | L46: Education | M46: 645 | N46: 4 | O46: Default | P46: 2021-07-26 | Q46: 0.4079
A47: LN-00566 | B47: Maria Taylor | C47: 31 | D47: Female | E47: Nairobi | F47: Business Owner | G47: 27 | H47: 1763246 | I47: 529565 | J47: 18.98 | K47: 12 | L47: Agriculture | M47: 821 | N47: 2 | O47: Late (31-60 days) | P47: 2023-09-02 | Q47: 0.3003
A48: LN-00645 | B48: Jasmine Villa | C48: 28 | D48: Female | E48: Nyeri | F48: Employed | G48: 13 | H48: 1852717 | I48: 170653 | J48: 15.92 | K48: 24 | L48: Medical | M48: 629 | N48: 4 | O48: Default | P48: 2023-07-07 | Q48: 0.0921
A49: LN-00283 | B49: Anita Frey | C49: 38 | D49: Male | E49: Mombasa | F49: Unemployed | G49: 8 | H49: 1222377 | I49: 752081 | J49: 12.63% | K49: 60 | L49: Medical | M49: 625 | N49: 1 | O49: Late (31-60 days) | P49: 2021-05-26 | Q49: 0.6153
A50: LN-01484 | B50: Charles Young | C50: 23 | D50: Male | E50: Nyeri | F50: Business Owner | G50: 5 | H50: 339292 | I50: 773890 | J50: 9.5 | K50: 36 | L50: Personal | M50: 560 | N50: 4 | O50: Charged Off | P50: 2022-11-17 | Q50: 2.2809
A51: LN-01399 | B51: Michele Pennington | C51: 64 | D51: Male | E51: Machakos | F51: Business Owner | G51: 21 | H51: 968140 | I51: 777634 | J51: 25.95 | K51: 12 | L51: Medical | M51: 686 | N51: 2 | O51: Charged Off | P51: 2022-07-18 | Q51: 0.8032
A52: LN-01197 | B52: Alexandra George | C52: 51 | D52: FEMALE | E52: Machakos | F52: Self-Employed | G52: 11 | H52: 1736396 | I52: 367823 | J52: 13.95 | K52: 60 | L52: Education | M52: 358 | N52: 4 | O52: Late (61-90 days) | P52: 2022-08-19 | Q52: 0.2118
A53: LN-00961 | B53: Phillip Velazquez | C53: 21 | D53: Female | E53: Kisumu | F53: Business Owner | G53: 28 | H53: 868725 | I53: 323602 | J53: 21.58 | K53: 24 | L53: Agriculture | M53: 375 | N53: 3 | O53: Charged Off | P53: 2023-03-10 | Q53: 0.3725
A54: LN-00254 | B54: Mary Willis | C54: 46 | D54: Female | E54: Nyeri | F54: Self-Employed | G54: 21 | H54: 2158281 | I54: 784265 | J54: 16.35 | K54: 60 | L54: Education | M54: 751 | N54: 1 | O54: Late (31-60 days) | P54: 2022-04-13 | Q54: 0.3634
A55: LN-00262 | B55: Jacqueline Terry | C55: 61 | D55: Male | E55: Nyeri | F55: Employed | G55: 5 | I55: 731111 | J55: 16.06 | K55: 24 | L55: Medical | N55: 1 | O55: Charged Off | P55: 2022-04-21 | Q55: 0.6068
A56: LN-00569 | B56: Dr. William Mack | C56: 29 | D56: Male | E56: Nakuru | F56: Business Owner | G56: 10 | H56: 2339081 | I56: 433089 | J56: 15.77 | K56: 48 | L56: Personal | M56: 841 | N56: 2 | O56: Fully Paid | P56: 2022-06-23 | Q56: 0.1852
A57: LN-01443 | B57: Victoria Smith | C57: 45 | D57: Male | E57: Mombasa | F57: Unemployed | G57: 13 | H57: 397770 | I57: 498454 | J57: 26.45 | K57: 60 | L57: Agriculture | M57: 500 | N57: 2 | O57: Fully Paid | P57: 2021-05-13 | Q57: 1.2531
A58: LN-00807 | B58: Leslie Long | C58: 46 | D58: Male | E58: Eldoret | F58: Unemployed | G58: 2 | H58: 209725 | I58: 80128 | J58: 15.16 | K58: 48 | L58: Medical | M58: 664 | N58: 5 | O58: Late (31-60 days) | P58: 2020-12-26 | Q58: 0.3821
A59: LN-00420 | B59: Bill Forbes | C59: 45 | D59: Female | E59: Kakamega | F59: Self-Employed | G59: 2 | H59: 885475 | I59: 325505 | J59: 25.72 | K59: 24 | L59: Education | M59: 703 | N59: 2 | O59: Late (31-60 days) | P59: 2020-03-31 | Q59: 0.3676
A60: LN-01431 | B60: Teresa Smith | C60: 45 | D60: Male | E60: Kisumu | F60: Self-Employed | G60: 0 | H60: 1202892 | I60: 154445 | J60: 9.06 | K60: 36 | L60: Medical | M60: 472 | N60: 3 | O60: Current | P60: 2021-01-23 | Q60: 0.1284
A61: LN-00890 | B61: Brian Duffy | C61: 56 | D61: Male | E61: Machakos | F61: Unemployed | G61: 13 | H61: 1275426 | I61: 448745 | J61: 8.5 | K61: 12 | L61: Medical | M61: 353 | N61: 5 | O61: Default | P61: 2021-01-14 | Q61: 0.3518
A62: LN-01161 | B62: Ryan Kelly | C62: 59 | D62: Female | E62: Machakos | F62: Self-Employed | G62: 17 | H62: 465711 | I62: 444671 | J62: 23.56 | K62: 12 | L62: Business | M62: 760 | N62: 5 | O62: Late (31-60 days) | P62: 2022-02-11 | Q62: 0.9548
A63: LN-00687 | B63: Brandon Salazar | C63: 47 | D63: Female | E63: Kisumu | F63: Business Owner | G63: 6 | H63: 1281928 | I63: 45991 | J63: 9.17 | K63: 12 | L63: Medical | M63: 346 | N63: 4 | O63: Charged Off | P63: 2023-01-07 | Q63: 0.0359
A64: LN-01032 | B64: Hannah Johnson | C64: 44 | D64: Male | E64: Eldoret | F64: Business Owner | G64: 2 | H64: 2048388 | I64: 256187 | J64: 20.91 | K64: 24 | L64: Personal | M64: 741 | N64: 0 | O64: Late (61-90 days) | P64: 2023-05-21 | Q64: 0.1251
A65: LN-00951 | B65: Stephen Mckinney | C65: 51 | D65: FEMALE | E65: Nakuru | F65: Employed | G65: 18 | I65: 790644 | J65: 20.99 | K65: 24 | L65: Medical | M65: 543 | N65: 6 | O65: Current | P65: 2023-06-20 | Q65: 0.387
A66: LN-01170 | B66: Emma Miranda | C66: 48 | D66: Male | E66: Nairobi | F66: Unemployed | G66: 20 | H66: 1156433 | I66: 707069 | J66: 25.15 | K66: 36 | L66: Home Improvement | M66: 469 | N66: 3 | O66: Late (31-60 days) | P66: 2022-04-21 | Q66: 0.6114
A67: LN-00994 | B67: Matthew Daniels | C67: 45 | D67: Female | E67: Kakamega | F67: Self-Employed | G67: 21 | H67: 2271635 | I67: 731413 | J67: 19.5 | K67: 36 | L67: Personal | M67: 413 | N67: 0 | O67: Default | P67: 2021-04-23 | Q67: 0.322
A68: LN-00489 | B68: Brooke Cantu | C68: 22 | D68: Female | E68: Eldoret | F68: Unemployed | G68: 16 | H68: 2234780 | I68: 69976 | J68: 9.2 | K68: 48 | L68: Business | M68: 831 | N68: 5 | O68: Fully Paid | P68: 2021-07-24 | Q68: 0.0313
A69: LN-01353 | B69: Katherine Thompson | C69: 45 | D69: Male | E69: Eldoret | F69: Employed | G69: 27 | H69: 1784642 | I69: 537039 | J69: 24.9 | K69: 36 | L69: Business | M69: 792 | N69: 5 | O69: Late (31-60 days) | P69: 2022-01-19 | Q69: 0.3009
A70: LN-01166 | B70: John Smith | C70: 39 | D70: Female | E70: Machakos | F70: Employed | G70: 22 | H70: 2205739 | I70: 204514 | J70: 23.09 | K70: 12 | L70: Medical | M70: 301 | N70: 4 | O70: Late (61-90 days) | P70: 2021-05-04 | Q70: 0.0927
A71: LN-00286 | B71: Anthony Mcclain DVM | C71: 36 | D71: Female | E71: Kisumu | F71: Self-Employed | G71: 14 | H71: 1248392 | I71: 457985 | J71: 27.16 | K71: 12 | L71: Home Improvement | M71: 623 | N71: 5 | O71: Charged Off | P71: 2023-02-01 | Q71: 0.3669
A72: LN-01159 | B72: Michael Adams Jr. | C72: 28 | D72: Male | E72: Mombasa | F72: Business Owner | G72: 16 | H72: 2104717 | I72: 393393 | J72: 25.32 | K72: 48 | L72: Business | M72: 621 | N72: 6 | O72: Late (31-60 days) | P72: 2023-02-04 | Q72: 0.1869
A73: LN-01306 | B73: Joshua Perry | C73: 39 | D73: Female | E73: Kisumu | F73: Unemployed | G73: 27 | H73: 1214262 | I73: 79821 | J73: 10.46 | K73: 24 | L73: Agriculture | N73: 7 | O73: Late (61-90 days) | P73: 2021-12-22 | Q73: 0.0657
A74: LN-01361 | B74: Aaron Flowers | C74: 52 | D74: Female | E74: Thika | F74: Self-Employed | G74: 13 | H74: 347647 | I74: 718148 | J74: 20.69 | K74: 60 | L74: Agriculture | M74: 680 | N74: 0 | O74: Current | P74: 2022-01-24 | Q74: 2.0657
A75: LN-01301 | B75: Michael Little | C75: 42 | D75: Male | E75: Nakuru | F75: Employed | G75: 22 | H75: 2115135 | I75: 475061 | J75: 13.96 | K75: 36 | L75: Personal | M75: 827 | N75: 2 | O75: Late (61-90 days) | P75: 2023-05-26 | Q75: 0.2246
A76: LN-00526 | B76: Kaitlin Owens | C76: 45 | D76: Male | E76: Machakos | F76: Unemployed | G76: 18 | H76: 1460617 | I76: 156213 | J76: 21.96 | K76: 24 | L76: Business | M76: 819 | N76: 6 | O76: Default | P76: 2023-10-05 | Q76: 0.107
A77: LN-00543 | B77: Adam Trujillo | C77: 48 | D77: Female | E77: Eldoret | F77: Business Owner | G77: 29 | H77: 1087669 | I77: 89087 | J77: 19.13 | K77: 12 | L77: Medical | M77: 642 | N77: 4 | O77: Current | P77: 2022-04-04 | Q77: 0.0819
A78: LN-00579 | B78: Erica Curry | C78: 47 | D78: Female | E78: Nairobi | F78: Business Owner | G78: 14 | H78: 1793325 | I78: 414754 | J78: 27.91 | K78: 24 | L78: Education | M78: 514 | N78: 6 | O78: Default | P78: 2022-11-21 | Q78: 0.2313
A79: LN-00671 | B79: Michael Scott | C79: 38 | D79: Female | E79: Nyeri | F79: Business Owner | G79: 19 | H79: 1513140 | I79: 517952 | J79: 9.23 | K79: 24 | L79: Personal | M79: 552 | N79: 5 | O79: Late (61-90 days) | P79: 2022-05-01 | Q79: 0.3423
A80: LN-01103 | B80: Ms. Nicole Hahn DDS | C80: 46 | D80: Male | E80: Kakamega | F80: Business Owner | G80: 23 | H80: 1191316 | I80: 240283 | J80: 27.65 | K80: 12 | L80: Home Improvement | M80: 345 | N80: 1 | O80: Charged Off | P80: 2022-09-19 | Q80: 0.2017
A81: LN-01379 | B81: Frank Gregory | C81: 51 | D81: Male | E81: Kisumu | F81: Unemployed | G81: 23 | H81: 1686145 | I81: 55903 | J81: 16.93 | K81: 60 | L81: Home Improvement | M81: 396 | N81: 7 | O81: Late (31-60 days) | P81: 2023-08-19 | Q81: 0.0332
A82: LN-00809 | B82: John Jackson | C82: 29 | D82: Female | E82: Eldoret | F82: Unemployed | G82: 28 | H82: 284555 | I82: 253540 | J82: 21.69 | K82: 60 | L82: Home Improvement | M82: 701 | N82: 2 | O82: Default | P82: 2023-08-25 | Q82: 0.891
A83: LN-01403 | B83: Christina Carr | C83: 49 | D83: Female | E83: Thika | F83: Self-Employed | G83: 1 | H83: 711972 | I83: 205639 | J83: 19.95 | K83: 60 | L83: Business | M83: -50 | N83: 5 | O83: Late (61-90 days) | P83: 2023-01-11 | Q83: 0.2888
A84: LN-00708 | B84: Michael Rhodes | C84: 39 | D84: Male | E84: Nyeri | F84: Unemployed | G84: 13 | H84: 2340682 | I84: 79778 | J84: 24.57 | K84: 12 | L84: Personal | M84: 681 | N84: 2 | O84: Default | P84: 2022-03-17 | Q84: 0.0341
A85: LN-00718 | B85: Christine Adams | C85: 52 | D85: Female | E85: Machakos | F85: Business Owner | G85: 15 | H85: 1208494 | I85: 634553 | J85: 27.42 | K85: 36 | L85: Education | M85: 602 | N85: 3 | O85: Default | P85: 2021-01-07 | Q85: 0.5251
A86: LN-00781 | B86: Gregory Lynch | C86: 24 | D86: Female | E86: Thika | F86: Business Owner | G86: 8 | H86: 1046183 | I86: 726291 | J86: 24.78 | K86: 48 | L86: Medical | M86: 457 | N86: 6 | O86: Late (61-90 days) | P86: 2021-09-09 | Q86: 0.6942
A87: LN-01334 | B87: Jared Giles | C87: 32 | D87: Female | E87: Machakos | F87: Self-Employed | G87: 1 | I87: 400714 | J87: 16.48 | K87: 48 | L87: Home Improvement | M87: 772 | N87: 0 | O87: Default | P87: 2023-01-09 | Q87: 0.2469
A88: LN-01468 | B88: Kyle Anderson | C88: 54 | D88: Male | E88: Meru | F88: Self-Employed | G88: 12 | H88: 1117635 | I88: 121407 | J88: 22.74 | K88: 24 | L88: Medical | M88: 1200 | N88: 5 | O88: Late (61-90 days) | P88: 2022-01-03 | Q88: 0.1086
A89: LN-01173 | B89: Douglas Wells | C89: 49 | D89: Female | E89: Nyeri | F89: Business Owner | G89: 15 | H89: 1700943 | I89: 609421 | J89: 14.91 | K89: 36 | L89: Education | M89: 771 | N89: 2 | O89: Current | P89: 2022-08-26 | Q89: 0.3583
A90: LN-00383 | B90: Alec Richardson | C90: 42 | D90: Male | E90: Nakuru | F90: Self-Employed | G90: 23 | H90: 259973 | I90: 410642 | J90: 16.52 | K90: 24 | L90: Business | M90: 440 | N90: 2 | O90: Late (61-90 days) | P90: 2020-11-19 | Q90: 1.5796
A91: LN-00719 | B91: Steven Peters | C91: 54 | D91: Female | E91: Eldoret | F91: Self-Employed | G91: 2 | H91: 1201318 | I91: 542154 | J91: 11.54 | K91: 60 | L91: Personal | M91: 749 | N91: 2 | O91: Default | P91: 2020-04-12 | Q91: 0.4513
A92: LN-00208 | B92: Michael Mcdonald | C92: 52 | D92: Male | E92: Eldoret | F92: Business Owner | G92: 14 | I92: 419371 | J92: 13.19 | K92: 48 | M92: 457 | N92: 2 | O92: Charged Off | P92: 2023-01-09 | Q92: 0.2047
A93: LN-01376 | B93: Jamie Lucero | C93: 43 | D93: Female | E93: Thika | F93: Business Owner | G93: 6 | H93: 1852795 | I93: 25750 | J93: 18.5 | K93: 36 | L93: Agriculture | M93: 726 | N93: 7 | O93: Charged Off | P93: 2021-11-02 | Q93: 0.0139
A94: LN-00157 | B94: Nicole Sherman | C94: 62 | D94: Female | E94: Eldoret | F94: Self-Employed | G94: 11 | H94: 1139192 | I94: 161365 | J94: 21.82 | K94: 12 | L94: Personal | M94: 631 | N94: 0 | O94: Charged Off | P94: 2021-11-27 | Q94: 0.1416
A95: LN-00649 | B95: Jeffrey Brown | C95: 48 | D95: Male | E95: Meru | F95: Self-Employed | G95: 19 | H95: 1421597 | I95: 772922 | J95: 26.69 | K95: 36 | L95: Personal | M95: 437 | N95: 5 | O95: Current | P95: 2020-06-07 | Q95: 0.5437
A96: LN-01249 | B96: Kristin Schmidt | C96: 46 | D96: Female | E96: Nyeri | F96: Self-Employed | G96: 23 | H96: 2255915 | I96: 719746 | J96: 15.84 | K96: 60 | L96: Medical | M96: 566 | N96: 1 | O96: Default | P96: 2023-06-02 | Q96: 0.319
A97: LN-00922 | B97: Mark Torres | C97: 57 | D97: Male | E97: Nairobi | F97: Self-Employed | G97: 11 | H97: 666799 | I97: 37413 | J97: 11.93 | K97: 60 | L97: Medical | M97: 577 | N97: 1 | O97: Late (61-90 days) | P97: 08-05-2021 | Q97: 0.0561
A98: LN-00505 | B98: Tracy Alvarez | C98: 56 | D98: Male | E98: Kisumu | F98: Business Owner | G98: 0 | H98: 583322 | I98: 760389 | J98: 16.53 | K98: 60 | L98: Education | M98: 692 | N98: 0 | O98: Late (31-60 days) | P98: 2020-03-19 | Q98: 1.3035
A99: LN-00311 | B99: Kathy Garcia | C99: 50 | D99: Male | E99: Nyeri | F99: Employed | G99: 29 | H99: 574274 | I99: 785419 | J99: 14.17 | K99: 12 | L99: Medical | M99: 799 | N99: 7 | O99: Default | P99: 2023-09-17 | Q99: 1.3677
A100: LN-01396 | B100: Meagan Calderon MD | C100: 60 | D100: Female | E100: Nakuru | F100: Employed | G100: 0 | H100: 1360788 | I100: 65619 | J100: 14.83 | K100: 12 | L100: Home Improvement | M100: 737 | N100: 4 | O100: Fully Paid | P100: 2023-01-05 | Q100: 0.0482
...

Sheet Cleaned_Loan_Data
A1: Loan_ID | B1: Helper_Column | C1: Customer_Name | D1: Age | E1: New_Age | F1: Gender | G1: New_Gender | H1: County | I1: Employment_Status | K1: New_Employment_Status | L1: Employment_Length_Years | M1: Annual_Income_KES | N1: New_Annual_Income | O1: Loan_Amount_KES | P1: Interest_Rate_Percent | Q1: Loan_Term_Months | R1: Loan_Purpose | S1: New_Loan_Purpose | T1: Credit_Score | U1: New_Credit_Score | V1: Num_Late_Payments | W1: Loan_Status | X1: Issue_Date | Y1: New_Date | Z1: Debt_To_Income_Ratio | AC1: Med Age | AD1: {=MEDIAN(IF((D2:D1517>=18)*(D2:D1517<=100), D2:D1517))} -> 44
A2: LN-00202 | B2: =IF(A2="", "MISSING", "OK") -> OK | C2: Carl West | D2: 3 | E2: =IF(OR(D2<18, D2>100),AD1,D2) -> 44 | F2: Male | G2: =IF(F2="", "Unknown", IF(OR(F2="F", F2="FEMALE", F2="Female"), "Female", IF(OR(F2="M", F2="MALE", F2="Male"), "Male", "Other"))) -> Male | H2: Nakuru | I2: Business Owner | K2: =IF(I2="", "Unknown", I2) -> Business Owner | L2: 7 | M2: 1777690 | N2: =IF(OR(M2="",M2<0),$AD$3,M2) -> 1777690 | O2: 49336 | P2: 11.45 | Q2: 48 | R2: Medical | S2: =IF(R2="", "Unknown", R2) -> Medical | T2: 417 | U2: =IF(OR(T2="",T2>999),$AD$2,T2) -> 417 | V2: 4 | W2: Late (31-60 days) | X2: 2020-12-04 | Y2: =IF(ISNUMBER(X2), X2, DATEVALUE(X2)) -> 44169 | Z2: 0.0278 | AC2: Med Cred | AD2: {=MEDIAN(IF((T2:T1517>=0)*(T2:T1517<=999),T2:T1517))} -> 556
A3: LN-00686 | B3: =IF(A3="", "MISSING", "OK") -> OK | C3: Misty Anderson | D3: 42 | E3: =IF(OR(D3<18, D3>100),AD2,D3) -> 42 | F3: Male | G3: =IF(F3="", "Unknown", IF(OR(F3="F", F3="FEMALE", F3="Female"), "Female", IF(OR(F3="M", F3="MALE", F3="Male"), "Male", "Other"))) -> Male | H3: Kisumu | I3: Employed | K3: =IF(I3="", "Unknown", I3) -> Employed | L3: 11 | M3: 1608080 | N3: =IF(OR(M3="",M3<0),$AD$3,M3) -> 1608080 | O3: 639064 | P3: 12.18 | Q3: 12 | R3: Personal | S3: =IF(R3="", "Unknown", R3) -> Personal | T3: 303 | U3: =IF(OR(T3="",T3>999),$AD$2,T3) -> 303 | V3: 0 | W3: Fully Paid | X3: 2022-05-08 | Y3: =IF(ISNUMBER(X3), X3, DATEVALUE(X3)) -> 44689 | Z3: 0.3974 | AC3: Med Inc | AD3: {=MEDIAN(IF(M2:M1517>0, M2:M1517))} -> 1333224
A4: LN-01423 | B4: =IF(A4="", "MISSING", "OK") -> OK | C4: Albert Bailey | D4: 59 | E4: =IF(OR(D4<18, D4>100),AD3,D4) -> 59 | F4: FEMALE | G4: =IF(F4="", "Unknown", IF(OR(F4="F", F4="FEMALE", F4="Female"), "Female", IF(OR(F4="M", F4="MALE", F4="Male"), "Male", "Other"))) -> Female | H4: Machakos | K4: =IF(I4="", "Unknown", I4) -> Unknown | L4: 26 | M4: 1342189 | N4: =IF(OR(M4="",M4<0),$AD$3,M4) -> 1342189 | O4: 694174 | P4: 25.16 | Q4: 36 | R4: Medical | S4: =IF(R4="", "Unknown", R4) -> Medical | T4: 676 | U4: =IF(OR(T4="",T4>999),$AD$2,T4) -> 676 | V4: 1 | W4: Fully Paid | X4: 2023-11-05 | Y4: =IF(ISNUMBER(X4), X4, DATEVALUE(X4)) -> 45235 | Z4: 0.5172
A5: LN-01136 | B5: =IF(A5="", "MISSING", "OK") -> OK | C5: Emily Barnes | D5: 21 | E5: =IF(OR(D5<18, D5>100),AD4,D5) -> 21 | F5: Female | G5: =IF(F5="", "Unknown", IF(OR(F5="F", F5="FEMALE", F5="Female"), "Female", IF(OR(F5="M", F5="MALE", F5="Male"), "Male", "Other"))) -> Female | H5: Kisumu | I5: Self-Employed | K5: =IF(I5="", "Unknown", I5) -> Self-Employed | L5: 15 | M5: 645982 | N5: =IF(OR(M5="",M5<0),$AD$3,M5) -> 645982 | O5: 104811 | P5: 22.48 | Q5: 24 | S5: =IF(R5="", "Unknown", R5) -> Unknown | T5: 591 | U5: =IF(OR(T5="",T5>999),$AD$2,T5) -> 591 | V5: 6 | W5: Late (31-60 days) | X5: 2021-01-25 | Y5: =IF(ISNUMBER(X5), X5, DATEVALUE(X5)) -> 44221 | Z5: 0.1623
A6: LN-00479 | B6: =IF(A6="", "MISSING", "OK") -> OK | C6: Troy Carrillo IV | D6: 21 | E6: =IF(OR(D6<18, D6>100),AD5,D6) -> 21 | F6: Female | G6: =IF(F6="", "Unknown", IF(OR(F6="F", F6="FEMALE", F6="Female"), "Female", IF(OR(F6="M", F6="MALE", F6="Male"), "Male", "Other"))) -> Female | H6: Thika | I6: Self-Employed | K6: =IF(I6="", "Unknown", I6) -> Self-Employed | L6: 11 | M6: -1386861 | N6: =IF(OR(M6="",M6<0),$AD$3,M6) -> 1333224 | O6: 667096 | P6: 19.51 | Q6: 12 | R6: Home Improvement | S6: =IF(R6="", "Unknown", R6) -> Home Improvement | T6: 786 | U6: =IF(OR(T6="",T6>999),$AD$2,T6) -> 786 | V6: 0 | W6: Current | X6: 44773 | Y6: =IF(ISNUMBER(X6), X6, DATEVALUE(X6)) -> 44773 | Z6: 0.481
A7: LN-00680 | B7: =IF(A7="", "MISSING", "OK") -> OK | C7: Gerald Mason | D7: 38 | E7: =IF(OR(D7<18, D7>100),AD6,D7) -> 38 | F7: Female | G7: =IF(F7="", "Unknown", IF(OR(F7="F", F7="FEMALE", F7="Female"), "Female", IF(OR(F7="M", F7="MALE", F7="Male"), "Male", "Other"))) -> Female | H7: Kakamega | I7: Business Owner | K7: =IF(I7="", "Unknown", I7) -> Business Owner | L7: 28 | M7: 2036231 | N7: =IF(OR(M7="",M7<0),$AD$3,M7) -> 2036231 | O7: 567219 | P7: 16.03 | Q7: 60 | R7: Medical | S7: =IF(R7="", "Unknown", R7) -> Medical | T7: 820 | U7: =IF(OR(T7="",T7>999),$AD$2,T7) -> 820 | V7: 2 | W7: Fully Paid | X7: 2022-02-18 | Y7: =IF(ISNUMBER(X7), X7, DATEVALUE(X7)) -> 44610 | Z7: 0.2786
A8: LN-01257 | B8: =IF(A8="", "MISSING", "OK") -> OK | C8: George Bass | D8: 41 | E8: =IF(OR(D8<18, D8>100),AD7,D8) -> 41 | F8: Male | G8: =IF(F8="", "Unknown", IF(OR(F8="F", F8="FEMALE", F8="Female"), "Female", IF(OR(F8="M", F8="MALE", F8="Male"), "Male", "Other"))) -> Male | H8: Nakuru | I8: Employed | K8: =IF(I8="", "Unknown", I8) -> Employed | L8: 27 | M8: 1266787 | N8: =IF(OR(M8="",M8<0),$AD$3,M8) -> 1266787 | O8: 614302 | P8: 14.85 | Q8: 36 | R8: Business | S8: =IF(R8="", "Unknown", R8) -> Business | T8: 441 | U8: =IF(OR(T8="",T8>999),$AD$2,T8) -> 441 | V8: 3 | W8: Current | X8: 2021-04-20 | Y8: =IF(ISNUMBER(X8), X8, DATEVALUE(X8)) -> 44306 | Z8: 0.4849
A9: LN-00161 | B9: =IF(A9="", "MISSING", "OK") -> OK | C9: Tyler Gillespie | D9: 8 | E9: =IF(OR(D9<18, D9>100),AD8,D9) -> 0 | F9: Female | G9: =IF(F9="", "Unknown", IF(OR(F9="F", F9="FEMALE", F9="Female"), "Female", IF(OR(F9="M", F9="MALE", F9="Male"), "Male", "Other"))) -> Female | H9: Machakos | I9: Self-Employed | K9: =IF(I9="", "Unknown", I9) -> Self-Employed | L9: 4 | M9: 2061175 | N9: =IF(OR(M9="",M9<0),$AD$3,M9) -> 2061175 | O9: 153172 | P9: 14.84 | Q9: 24 | R9: Medical | S9: =IF(R9="", "Unknown", R9) -> Medical | T9: 402 | U9: =IF(OR(T9="",T9>999),$AD$2,T9) -> 402 | V9: 5 | W9: Current | X9: 2020-11-19 | Y9: =IF(ISNUMBER(X9), X9, DATEVALUE(X9)) -> 44154 | Z9: 0.0743
A10: LN-00499 | B10: =IF(A10="", "MISSING", "OK") -> OK | C10: Robert Randall | D10: 54 | E10: =IF(OR(D10<18, D10>100),AD9,D10) -> 54 | F10: Male | G10: =IF(F10="", "Unknown", IF(OR(F10="F", F10="FEMALE", F10="Female"), "Female", IF(OR(F10="M", F10="MALE", F10="Male"), "Male", "Other"))) -> Male | H10: Thika | I10: Self-Employed | K10: =IF(I10="", "Unknown", I10) -> Self-Employed | L10: 27 | M10: 874892 | N10: =IF(OR(M10="",M10<0),$AD$3,M10) -> 874892 | O10: 733087 | P10: 17.31 | Q10: 60 | R10: Medical | S10: =IF(R10="", "Unknown", R10) -> Medical | T10: 766 | U10: =IF(OR(T10="",T10>999),$AD$2,T10) -> 766 | V10: 7 | W10: Charged Off | X10: 2020-02-26 | Y10: =IF(ISNUMBER(X10), X10, DATEVALUE(X10)) -> 43887 | Z10: 0.8379
A11: LN-01250 | B11: =IF(A11="", "MISSING", "OK") -> OK | C11: Nancy Fields | D11: 49 | E11: =IF(OR(D11<18, D11>100),AD10,D11) -> 49 | F11: Male | G11: =IF(F11="", "Unknown", IF(OR(F11="F", F11="FEMALE", F11="Female"), "Female", IF(OR(F11="M", F11="MALE", F11="Male"), "Male", "Other"))) -> Male | H11: Kakamega | I11: Unemployed | K11: =IF(I11="", "Unknown", I11) -> Unemployed | L11: 16 | M11: 827341 | N11: =IF(OR(M11="",M11<0),$AD$3,M11) -> 827341 | O11: 798754 | P11: 26.96 | Q11: 24 | R11: Agriculture | S11: =IF(R11="", "Unknown", R11) -> Agriculture | T11: 840 | U11: =IF(OR(T11="",T11>999),$AD$2,T11) -> 840 | V11: 3 | W11: Fully Paid | X11: 2022-02-22 | Y11: =IF(ISNUMBER(X11), X11, DATEVALUE(X11)) -> 44614 | Z11: 0.9654
A12: LN-01413 | B12: =IF(A12="", "MISSING", "OK") -> OK | C12: Paul Williams | D12: 55 | E12: =IF(OR(D12<18, D12>100),AD11,D12) -> 55 | F12: Male | G12: =IF(F12="", "Unknown", IF(OR(F12="F", F12="FEMALE", F12="Female"), "Female", IF(OR(F12="M", F12="MALE", F12="Male"), "Male", "Other"))) -> Male | H12: Nyeri | I12: Business Owner | K12: =IF(I12="", "Unknown", I12) -> Business Owner | L12: 24 | M12: 1596953 | N12: =IF(OR(M12="",M12<0),$AD$3,M12) -> 1596953 | O12: 523323 | P12: 16.61 | Q12: 48 | R12: Medical | S12: =IF(R12="", "Unknown", R12) -> Medical | T12: 644 | U12: =IF(OR(T12="",T12>999),$AD$2,T12) -> 644 | V12: 5 | W12: Late (31-60 days) | X12: 2021-07-26 | Y12: =IF(ISNUMBER(X12), X12, DATEVALUE(X12)) -> 44403 | Z12: 0.3277
A13: LN-00087 | B13: =IF(A13="", "MISSING", "OK") -> OK | C13: Michael Mckee | D13: 21 | E13: =IF(OR(D13<18, D13>100),AD12,D13) -> 21 | F13: Male | G13: =IF(F13="", "Unknown", IF(OR(F13="F", F13="FEMALE", F13="Female"), "Female", IF(OR(F13="M", F13="MALE", F13="Male"), "Male", "Other"))) -> Male | H13: Kisumu | I13: Unemployed | K13: =IF(I13="", "Unknown", I13) -> Unemployed | L13: 11 | M13: 1141568 | N13: =IF(OR(M13="",M13<0),$AD$3,M13) -> 1141568 | O13: 118538 | P13: 12.74 | Q13: 60 | S13: =IF(R13="", "Unknown", R13) -> Unknown | T13: 306 | U13: =IF(OR(T13="",T13>999),$AD$2,T13) -> 306 | V13: 1 | W13: Fully Paid | X13: 2023-07-24 | Y13: =IF(ISNUMBER(X13), X13, DATEVALUE(X13)) -> 45131 | Z13: 0.1038
A14: LN-01498 | B14: =IF(A14="", "MISSING", "OK") -> OK | C14: Ashley Stout | D14: 48 | E14: =IF(OR(D14<18, D14>100),AD13,D14) -> 48 | F14: Male | G14: =IF(F14="", "Unknown", IF(OR(F14="F", F14="FEMALE", F14="Female"), "Female", IF(OR(F14="M", F14="MALE", F14="Male"), "Male", "Other"))) -> Male | H14: Nairobi | I14: Employed | K14: =IF(I14="", "Unknown", I14) -> Employed | L14: 23 | M14: 2043462 | N14: =IF(OR(M14="",M14<0),$AD$3,M14) -> 2043462 | O14: 546169 | P14: 8.9 | Q14: 60 | R14: Home Improvement | S14: =IF(R14="", "Unknown", R14) -> Home Improvement | T14: 785 | U14: =IF(OR(T14="",T14>999),$AD$2,T14) -> 785 | V14: 3 | W14: Late (61-90 days) | X14: 2020-05-04 | Y14: =IF(ISNUMBER(X14), X14, DATEVALUE(X14)) -> 43955 | Z14: 0.2673
A15: LN-00308 | B15: =IF(A15="", "MISSING", "OK") -> OK | C15: Meagan Fernandez | D15: 47 | E15: =IF(OR(D15<18, D15>100),AD14,D15) -> 47 | F15: Male | G15: =IF(F15="", "Unknown", IF(OR(F15="F", F15="FEMALE", F15="Female"), "Female", IF(OR(F15="M", F15="MALE", F15="Male"), "Male", "Other"))) -> Male | H15: Mombasa | I15: Self-Employed | K15: =IF(I15="", "Unknown", I15) -> Self-Employed | L15: 20 | M15: 1387068 | N15: =IF(OR(M15="",M15<0),$AD$3,M15) -> 1387068 | O15: 128042 | P15: 24.88 | Q15: 60 | R15: Personal | S15: =IF(R15="", "Unknown", R15) -> Personal | T15: 813 | U15: =IF(OR(T15="",T15>999),$AD$2,T15) -> 813 | V15: 7 | W15: Default | X15: 2022-05-16 | Y15: =IF(ISNUMBER(X15), X15, DATEVALUE(X15)) -> 44697 | Z15: 0.0923
A16: LN-00663 | B16: =IF(A16="", "MISSING", "OK") -> OK | C16: Kelly Gomez | D16: 53 | E16: =IF(OR(D16<18, D16>100),AD15,D16) -> 53 | F16: Female | G16: =IF(F16="", "Unknown", IF(OR(F16="F", F16="FEMALE", F16="Female"), "Female", IF(OR(F16="M", F16="MALE", F16="Male"), "Male", "Other"))) -> Female | H16: Nyeri | I16: Employed | K16: =IF(I16="", "Unknown", I16) -> Employed | L16: 2 | M16: 1865996 | N16: =IF(OR(M16="",M16<0),$AD$3,M16) -> 1865996 | O16: 626226 | P16: 16.01 | Q16: 36 | R16: Home Improvement | S16: =IF(R16="", "Unknown", R16) -> Home Improvement | T16: 609 | U16: =IF(OR(T16="",T16>999),$AD$2,T16) -> 609 | V16: 2 | W16: Charged Off | X16: 2023-12-17 | Y16: =IF(ISNUMBER(X16), X16, DATEVALUE(X16)) -> 45277 | Z16: 0.3356
A17: LN-00019 | B17: =IF(A17="", "MISSING", "OK") -> OK | C17: Shawn Wong DDS | D17: 44 | E17: =IF(OR(D17<18, D17>100),AD16,D17) -> 44 | F17: Male | G17: =IF(F17="", "Unknown", IF(OR(F17="F", F17="FEMALE", F17="Female"), "Female", IF(OR(F17="M", F17="MALE", F17="Male"), "Male", "Other"))) -> Male | H17: Thika | I17: Self-Employed | K17: =IF(I17="", "Unknown", I17) -> Self-Employed | L17: 15 | M17: 2165209 | N17: =IF(OR(M17="",M17<0),$AD$3,M17) -> 2165209 | O17: 687505 | P17: 9.74 | Q17: 24 | R17: Medical | S17: =IF(R17="", "Unknown", R17) -> Medical | T17: 436 | U17: =IF(OR(T17="",T17>999),$AD$2,T17) -> 436 | V17: 3 | W17: Late (31-60 days) | X17: 2022-10-31 | Y17: =IF(ISNUMBER(X17), X17, DATEVALUE(X17)) -> 44865 | Z17: 0.3175
A18: LN-00723 | B18: =IF(A18="", "MISSING", "OK") -> OK | C18: Casey Hall | D18: 59 | E18: =IF(OR(D18<18, D18>100),AD17,D18) -> 59 | F18: Female | G18: =IF(F18="", "Unknown", IF(OR(F18="F", F18="FEMALE", F18="Female"), "Female", IF(OR(F18="M", F18="MALE", F18="Male"), "Male", "Other"))) -> Female | H18: Eldoret | I18: Unemployed | K18: =IF(I18="", "Unknown", I18) -> Unemployed | L18: 21 | M18: 809085 | N18: =IF(OR(M18="",M18<0),$AD$3,M18) -> 809085 | O18: 50949 | P18: 18.33 | Q18: 24 | R18: Medical | S18: =IF(R18="", "Unknown", R18) -> Medical | T18: 302 | U18: =IF(OR(T18="",T18>999),$AD$2,T18) -> 302 | V18: 0 | W18: Fully Paid | X18: 2021-03-09 | Y18: =IF(ISNUMBER(X18), X18, DATEVALUE(X18)) -> 44264 | Z18: 0.063
A19: LN-01231 | B19: =IF(A19="", "MISSING", "OK") -> OK | C19: Terri Kim | D19: 44 | E19: =IF(OR(D19<18, D19>100),AD18,D19) -> 44 | F19: Female | G19: =IF(F19="", "Unknown", IF(OR(F19="F", F19="FEMALE", F19="Female"), "Female", IF(OR(F19="M", F19="MALE", F19="Male"), "Male", "Other"))) -> Female | H19: Machakos | I19: Business Owner | K19: =IF(I19="", "Unknown", I19) -> Business Owner | L19: 19 | M19: 1823312 | N19: =IF(OR(M19="",M19<0),$AD$3,M19) -> 1823312 | O19: 221202 | P19: 11.35 | Q19: 36 | R19: Education | S19: =IF(R19="", "Unknown", R19) -> Education | T19: 488 | U19: =IF(OR(T19="",T19>999),$AD$2,T19) -> 488 | V19: 3 | W19: Late (61-90 days) | X19: 2020-02-29 | Y19: =IF(ISNUMBER(X19), X19, DATEVALUE(X19)) -> 43890 | Z19: 0.1213
A20: LN-00142 | B20: =IF(A20="", "MISSING", "OK") -> OK | C20: Jennifer Booker | D20: 24 | E20: =IF(OR(D20<18, D20>100),AD19,D20) -> 24 | F20: Female | G20: =IF(F20="", "Unknown", IF(OR(F20="F", F20="FEMALE", F20="Female"), "Female", IF(OR(F20="M", F20="MALE", F20="Male"), "Male", "Other"))) -> Female | H20: Thika | I20: Unemployed | K20: =IF(I20="", "Unknown", I20) -> Unemployed | L20: 9 | M20: 259083 | N20: =IF(OR(M20="",M20<0),$AD$3,M20) -> 259083 | O20: 329521 | P20: 23.08 | Q20: 24 | R20: Agriculture | S20: =IF(R20="", "Unknown", R20) -> Agriculture | T20: 680 | U20: =IF(OR(T20="",T20>999),$AD$2,T20) -> 680 | V20: 7 | W20: Current | X20: 2020-05-10 | Y20: =IF(ISNUMBER(X20), X20, DATEVALUE(X20)) -> 43961 | Z20: 1.2719
A21: LN-00454 | B21: =IF(A21="", "MISSING", "OK") -> OK | C21: Jamie Savage | D21: 54 | E21: =IF(OR(D21<18, D21>100),AD20,D21) -> 54 | F21: Male | G21: =IF(F21="", "Unknown", IF(OR(F21="F", F21="FEMALE", F21="Female"), "Female", IF(OR(F21="M", F21="MALE", F21="Male"), "Male", "Other"))) -> Male | H21: Nakuru | I21: Unemployed | K21: =IF(I21="", "Unknown", I21) -> Unemployed | L21: 16 | M21: 741672 | N21: =IF(OR(M21="",M21<0),$AD$3,M21) -> 741672 | O21: 245391 | P21: 26.69 | Q21: 48 | R21: Medical | S21: =IF(R21="", "Unknown", R21) -> Medical | T21: 552 | U21: =IF(OR(T21="",T21>999),$AD$2,T21) -> 552 | V21: 1 | W21: Fully Paid | X21: 2020-07-29 | Y21: =IF(ISNUMBER(X21), X21, DATEVALUE(X21)) -> 44041 | Z21: 0.3309
A22: LN-01192 | B22: =IF(A22="", "MISSING", "OK") -> OK | C22: Tiffany Chavez | D22: 36 | E22: =IF(OR(D22<18, D22>100),AD21,D22) -> 36 | F22: Male | G22: =IF(F22="", "Unknown", IF(OR(F22="F", F22="FEMALE", F22="Female"), "Female", IF(OR(F22="M", F22="MALE", F22="Male"), "Male", "Other"))) -> Male | H22: Meru | I22: Unemployed | K22: =IF(I22="", "Unknown", I22) -> Unemployed | L22: 18 | M22: 1730184 | N22: =IF(OR(M22="",M22<0),$AD$3,M22) -> 1730184 | O22: 176255 | P22: 17.86 | Q22: 48 | R22: Business | S22: =IF(R22="", "Unknown", R22) -> Business | T22: 422 | U22: =IF(OR(T22="",T22>999),$AD$2,T22) -> 422 | V22: 4 | W22: Charged Off | X22: 2020-10-22 | Y22: =IF(ISNUMBER(X22), X22, DATEVALUE(X22)) -> 44126 | Z22: 0.1019
A23: LN-00330 | B23: =IF(A23="", "MISSING", "OK") -> OK | C23: Randy Williams | D23: 51 | E23: =IF(OR(D23<18, D23>100),AD22,D23) -> 51 | F23: Male | G23: =IF(F23="", "Unknown", IF(OR(F23="F", F23="FEMALE", F23="Female"), "Female", IF(OR(F23="M", F23="MALE", F23="Male"), "Male", "Other"))) -> Male | H23: Nakuru | I23: Business Owner | K23: =IF(I23="", "Unknown", I23) -> Business Owner | L23: 1 | M23: 2228891 | N23: =IF(OR(M23="",M23<0),$AD$3,M23) -> 2228891 | O23: 733987 | P23: 20.07 | Q23: 60 | R23: Agriculture | S23: =IF(R23="", "Unknown", R23) -> Agriculture | T23: 365 | U23: =IF(OR(T23="",T23>999),$AD$2,T23) -> 365 | V23: 4 | W23: Fully Paid | X23: 2022-11-06 | Y23: =IF(ISNUMBER(X23), X23, DATEVALUE(X23)) -> 44871 | Z23: 0.3293
A24: LN-01355 | B24: =IF(A24="", "MISSING", "OK") -> OK | C24: Michael Herrera | D24: 45 | E24: =IF(OR(D24<18, D24>100),AD23,D24) -> 45 | F24: Female | G24: =IF(F24="", "Unknown", IF(OR(F24="F", F24="FEMALE", F24="Female"), "Female", IF(OR(F24="M", F24="MALE", F24="Male"), "Male", "Other"))) -> Female | H24: Eldoret | I24: Employed | K24: =IF(I24="", "Unknown", I24) -> Employed | L24: 1 | M24: 2152424 | N24: =IF(OR(M24="",M24<0),$AD$3,M24) -> 2152424 | O24: 125686 | P24: 9.03 | Q24: 48 | R24: Agriculture | S24: =IF(R24="", "Unknown", R24) -> Agriculture | T24: 472 | U24: =IF(OR(T24="",T24>999),$AD$2,T24) -> 472 | V24: 3 | W24: Late (61-90 days) | X24: 2022-03-19 | Y24: =IF(ISNUMBER(X24), X24, DATEVALUE(X24)) -> 44639 | Z24: 0.0584
A25: LN-00739 | B25: =IF(A25="", "MISSING", "OK") -> OK | C25: Robert Sellers MD | D25: 22 | E25: =IF(OR(D25<18, D25>100),AD24,D25) -> 22 | F25: Male | G25: =IF(F25="", "Unknown", IF(OR(F25="F", F25="FEMALE", F25="Female"), "Female", IF(OR(F25="M", F25="MALE", F25="Male"), "Male", "Other"))) -> Male | H25: Nakuru | I25: Business Owner | K25: =IF(I25="", "Unknown", I25) -> Business Owner | L25: 20 | M25: 1123693 | N25: =IF(OR(M25="",M25<0),$AD$3,M25) -> 1123693 | O25: 393216 | P25: 9.09 | Q25: 12 | R25: Business | S25: =IF(R25="", "Unknown", R25) -> Business | T25: 498 | U25: =IF(OR(T25="",T25>999),$AD$2,T25) -> 498 | V25: 3 | W25: Late (31-60 days) | X25: 2020-05-20 | Y25: =IF(ISNUMBER(X25), X25, DATEVALUE(X25)) -> 43971 | Z25: 0.3499
A26: LN-00492 | B26: =IF(A26="", "MISSING", "OK") -> OK | C26: Mark Guerrero | D26: 37 | E26: =IF(OR(D26<18, D26>100),AD25,D26) -> 37 | G26: =IF(F26="", "Unknown", IF(OR(F26="F", F26="FEMALE", F26="Female"), "Female", IF(OR(F26="M", F26="MALE", F26="Male"), "Male", "Other"))) -> Unknown | H26: Nairobi | I26: Self-Employed | K26: =IF(I26="", "Unknown", I26) -> Self-Employed | L26: 6 | M26: 373510 | N26: =IF(OR(M26="",M26<0),$AD$3,M26) -> 373510 | O26: 241883 | P26: 24.99 | Q26: 24 | R26: Home Improvement | S26: =IF(R26="", "Unknown", R26) -> Home Improvement | T26: 804 | U26: =IF(OR(T26="",T26>999),$AD$2,T26) -> 804 | V26: 2 | W26: Charged Off | X26: 2021-12-20 | Y26: =IF(ISNUMBER(X26), X26, DATEVALUE(X26)) -> 44550 | Z26: 0.6476
A27: LN-00656 | B27: =IF(A27="", "MISSING", "OK") -> OK | C27: Austin Joyce | D27: 48 | E27: =IF(OR(D27<18, D27>100),AD26,D27) -> 48 | F27: Male | G27: =IF(F27="", "Unknown", IF(OR(F27="F", F27="FEMALE", F27="Female"), "Female", IF(OR(F27="M", F27="MALE", F27="Male"), "Male", "Other"))) -> Male | H27: Kisumu | I27: Unemployed | K27: =IF(I27="", "Unknown", I27) -> Unemployed | L27: 14 | M27: 1859161 | N27: =IF(OR(M27="",M27<0),$AD$3,M27) -> 1859161 | O27: 174692 | P27: 14.79 | Q27: 60 | R27: Medical | S27: =IF(R27="", "Unknown", R27) -> Medical | T27: 552 | U27: =IF(OR(T27="",T27>999),$AD$2,T27) -> 552 | V27: 5 | W27: Late (31-60 days) | X27: 2020-06-14 | Y27: =IF(ISNUMBER(X27), X27, DATEVALUE(X27)) -> 43996 | Z27: 0.094
A28: LN-01429 | B28: =IF(A28="", "MISSING", "OK") -> OK | C28: Sandra Johnson | D28: 30 | E28: =IF(OR(D28<18, D28>100),AD27,D28) -> 30 | F28: Female | G28: =IF(F28="", "Unknown", IF(OR(F28="F", F28="FEMALE", F28="Female"), "Female", IF(OR(F28="M", F28="MALE", F28="Male"), "Male", "Other"))) -> Female | H28: Mombasa | I28: Business Owner | K28: =IF(I28="", "Unknown", I28) -> Business Owner | L28: 2 | M28: 305438 | N28: =IF(OR(M28="",M28<0),$AD$3,M28) -> 305438 | O28: 589354 | P28: 18.55 | Q28: 60 | R28: Home Improvement | S28: =IF(R28="", "Unknown", R28) -> Home Improvement | T28: 328 | U28: =IF(OR(T28="",T28>999),$AD$2,T28) -> 328 | V28: 6 | W28: Default | X28: 2022-03-26 | Y28: =IF(ISNUMBER(X28), X28, DATEVALUE(X28)) -> 44646 | Z28: 1.9295
A29: LN-00309 | B29: =IF(A29="", "MISSING", "OK") -> OK | C29: Brenda Pitts | D29: 54 | E29: =IF(OR(D29<18, D29>100),AD28,D29) -> 54 | F29: Female | G29: =IF(F29="", "Unknown", IF(OR(F29="F", F29="FEMALE", F29="Female"), "Female", IF(OR(F29="M", F29="MALE", F29="Male"), "Male", "Other"))) -> Female | H29: Nakuru | I29: Business Owner | K29: =IF(I29="", "Unknown", I29) -> Business Owner | L29: 25 | M29: 1702688 | N29: =IF(OR(M29="",M29<0),$AD$3,M29) -> 1702688 | O29: 74110 | P29: 17.68 | Q29: 60 | R29: Agriculture | S29: =IF(R29="", "Unknown", R29) -> Agriculture | T29: 802 | U29: =IF(OR(T29="",T29>999),$AD$2,T29) -> 802 | V29: 6 | W29: Charged Off | X29: 2023-11-27 | Y29: =IF(ISNUMBER(X29), X29, DATEVALUE(X29)) -> 45257 | Z29: 0.0435
A30: LN-00938 | B30: =IF(A30="", "MISSING", "OK") -> OK | C30: Christian Douglas | D30: 22 | E30: =IF(OR(D30<18, D30>100),AD29,D30) -> 22 | F30: Female | G30: =IF(F30="", "Unknown", IF(OR(F30="F", F30="FEMALE", F30="Female"), "Female", IF(OR(F30="M", F30="MALE", F30="Male"), "Male", "Other"))) -> Female | H30: Machakos | I30: Employed | K30: =IF(I30="", "Unknown", I30) -> Employed | L30: 1 | M30: 1636081 | N30: =IF(OR(M30="",M30<0),$AD$3,M30) -> 1636081 | O30: 210920 | P30: 19.1 | Q30: 24 | R30: Agriculture | S30: =IF(R30="", "Unknown", R30) -> Agriculture | T30: 809 | U30: =IF(OR(T30="",T30>999),$AD$2,T30) -> 809 | V30: 5 | W30: Charged Off | X30: 2023-11-06 | Y30: =IF(ISNUMBER(X30), X30, DATEVALUE(X30)) -> 45236 | Z30: 0.1289
A31: LN-00288 | B31: =IF(A31="", "MISSING", "OK") -> OK | C31: Janet Johnson | D31: 56 | E31: =IF(OR(D31<18, D31>100),AD30,D31) -> 56 | F31: Female | G31: =IF(F31="", "Unknown", IF(OR(F31="F", F31="FEMALE", F31="Female"), "Female", IF(OR(F31="M", F31="MALE", F31="Male"), "Male", "Other"))) -> Female | H31: Machakos | I31: Employed | K31: =IF(I31="", "Unknown", I31) -> Employed | L31: 18 | M31: 1103780 | N31: =IF(OR(M31="",M31<0),$AD$3,M31) -> 1103780 | O31: 515164 | P31: 25.72 | Q31: 36 | R31: Home Improvement | S31: =IF(R31="", "Unknown", R31) -> Home Improvement | T31: 464 | U31: =IF(OR(T31="",T31>999),$AD$2,T31) -> 464 | V31: 4 | W31: Fully Paid | X31: 2020-04-13 | Y31: =IF(ISNUMBER(X31), X31, DATEVALUE(X31)) -> 43934 | Z31: 0.4667
A32: LN-01415 | B32: =IF(A32="", "MISSING", "OK") -> OK | C32: Samuel Smith | D32: 54 | E32: =IF(OR(D32<18, D32>100),AD31,D32) -> 54 | F32: Male | G32: =IF(F32="", "Unknown", IF(OR(F32="F", F32="FEMALE", F32="Female"), "Female", IF(OR(F32="M", F32="MALE", F32="Male"), "Male", "Other"))) -> Male | H32: Meru | I32: Employed | K32: =IF(I32="", "Unknown", I32) -> Employed | L32: 3 | M32: 601280 | N32: =IF(OR(M32="",M32<0),$AD$3,M32) -> 601280 | O32: 797635 | P32: 22.13 | Q32: 24 | R32: Agriculture | S32: =IF(R32="", "Unknown", R32) -> Agriculture | T32: 849 | U32: =IF(OR(T32="",T32>999),$AD$2,T32) -> 849 | V32: 2 | W32: Default | X32: 11-14-2023 | Y32: =IF(ISNUMBER(X32), X32, DATEVALUE(X32)) -> 45244 | Z32: 1.3266
A33: LN-00468 | B33: =IF(A33="", "MISSING", "OK") -> OK | C33: Joseph Cortez MD | D33: 47 | E33: =IF(OR(D33<18, D33>100),AD32,D33) -> 47 | F33: Female | G33: =IF(F33="", "Unknown", IF(OR(F33="F", F33="FEMALE", F33="Female"), "Female", IF(OR(F33="M", F33="MALE", F33="Male"), "Male", "Other"))) -> Female | H33: Thika | I33: Employed | K33: =IF(I33="", "Unknown", I33) -> Employed | L33: 17 | M33: 691083 | N33: =IF(OR(M33="",M33<0),$AD$3,M33) -> 691083 | O33: 396087 | P33: 25.31 | Q33: 12 | R33: Agriculture | S33: =IF(R33="", "Unknown", R33) -> Agriculture | T33: 449 | U33: =IF(OR(T33="",T33>999),$AD$2,T33) -> 449 | V33: 6 | W33: Late (61-90 days) | X33: 2023-10-03 | Y33: =IF(ISNUMBER(X33), X33, DATEVALUE(X33)) -> 45202 | Z33: 0.5731
A34: LN-00448 | B34: =IF(A34="", "MISSING", "OK") -> OK | C34: Richard Gonzalez | D34: 50 | E34: =IF(OR(D34<18, D34>100),AD33,D34) -> 50 | F34: Female | G34: =IF(F34="", "Unknown", IF(OR(F34="F", F34="FEMALE", F34="Female"), "Female", IF(OR(F34="M", F34="MALE", F34="Male"), "Male", "Other"))) -> Female | H34: Nairobi | I34: Business Owner | K34: =IF(I34="", "Unknown", I34) -> Business Owner | L34: 6 | M34: 746956 | N34: =IF(OR(M34="",M34<0),$AD$3,M34) -> 746956 | O34: 407699 | P34: 16.22 | Q34: 12 | R34: Agriculture | S34: =IF(R34="", "Unknown", R34) -> Agriculture | T34: 725 | U34: =IF(OR(T34="",T34>999),$AD$2,T34) -> 725 | V34: 6 | W34: current | X34: 2020-03-22 | Y34: =IF(ISNUMBER(X34), X34, DATEVALUE(X34)) -> 43912 | Z34: 0.5458
A35: LN-01117 | B35: =IF(A35="", "MISSING", "OK") -> OK | C35: Steven Hernandez | D35: 27 | E35: =IF(OR(D35<18, D35>100),AD34,D35) -> 27 | F35: Male | G35: =IF(F35="", "Unknown", IF(OR(F35="F", F35="FEMALE", F35="Female"), "Female", IF(OR(F35="M", F35="MALE", F35="Male"), "Male", "Other"))) -> Male | H35: Nairobi | I35: Employed | K35: =IF(I35="", "Unknown", I35) -> Employed | L35: 28 | M35: 656513 | N35: =IF(OR(M35="",M35<0),$AD$3,M35) -> 656513 | O35: 83972 | P35: 23.04 | Q35: 48 | R35: Business | S35: =IF(R35="", "Unknown", R35) -> Business | T35: 681 | U35: =IF(OR(T35="",T35>999),$AD$2,T35) -> 681 | V35: 6 | W35: Default | X35: 2021-04-05 | Y35: =IF(ISNUMBER(X35), X35, DATEVALUE(X35)) -> 44291 | Z35: 0.1279
A36: LN-01028 | B36: =IF(A36="", "MISSING", "OK") -> OK | C36: Scott Pham | D36: 58 | E36: =IF(OR(D36<18, D36>100),AD35,D36) -> 58 | F36: Female | G36: =IF(F36="", "Unknown", IF(OR(F36="F", F36="FEMALE", F36="Female"), "Female", IF(OR(F36="M", F36="MALE", F36="Male"), "Male", "Other"))) -> Female | H36: Machakos | I36: Business Owner | K36: =IF(I36="", "Unknown", I36) -> Business Owner | L36: 11 | M36: -551616 | N36: =IF(OR(M36="",M36<0),$AD$3,M36) -> 1333224 | O36: 686015 | P36: 26.9 | Q36: 48 | R36: Home Improvement | S36: =IF(R36="", "Unknown", R36) -> Home Improvement | T36: 628 | U36: =IF(OR(T36="",T36>999),$AD$2,T36) -> 628 | V36: 1 | W36: Charged Off | X36: 2023-05-09 | Y36: =IF(ISNUMBER(X36), X36, DATEVALUE(X36)) -> 45055 | Z36: 1.2436
A37: LN-00637 | B37: =IF(A37="", "MISSING", "OK") -> OK | C37: Matthew Salazar | D37: 23 | E37: =IF(OR(D37<18, D37>100),AD36,D37) -> 23 | F37: Female | G37: =IF(F37="", "Unknown", IF(OR(F37="F", F37="FEMALE", F37="Female"), "Female", IF(OR(F37="M", F37="MALE", F37="Male"), "Male", "Other"))) -> Female | H37: Nyeri | I37: Employed | K37: =IF(I37="", "Unknown", I37) -> Employed | L37: 5 | M37: 1724613 | N37: =IF(OR(M37="",M37<0),$AD$3,M37) -> 1724613 | O37: 425105 | P37: 26.23 | Q37: 12 | R37: Business | S37: =IF(R37="", "Unknown", R37) -> Business | T37: 596 | U37: =IF(OR(T37="",T37>999),$AD$2,T37) -> 596 | V37: 7 | W37: Late (31-60 days) | X37: 2022-08-30 | Y37: =IF(ISNUMBER(X37), X37, DATEVALUE(X37)) -> 44803 | Z37: 0.2465
A38: LN-00075 | B38: =IF(A38="", "MISSING", "OK") -> OK | C38: Susan Taylor | D38: 34 | E38: =IF(OR(D38<18, D38>100),AD37,D38) -> 34 | F38: male | G38: =IF(F38="", "Unknown", IF(OR(F38="F", F38="FEMALE", F38="Female"), "Female", IF(OR(F38="M", F38="MALE", F38="Male"), "Male", "Other"))) -> Male | H38: Kakamega | I38: Employed | K38: =IF(I38="", "Unknown", I38) -> Employed | L38: 14 | M38: 777897 | N38: =IF(OR(M38="",M38<0),$AD$3,M38) -> 777897 | O38: 411858 | P38: 8.99 | Q38: 24 | R38: Home Improvement | S38: =IF(R38="", "Unknown", R38) -> Home Improvement | T38: 552 | U38: =IF(OR(T38="",T38>999),$AD$2,T38) -> 552 | V38: 2 | W38: Current | X38: 2022-01-17 | Y38: =IF(ISNUMBER(X38), X38, DATEVALUE(X38)) -> 44578 | Z38: 0.5295
A39: LN-01481 | B39: =IF(A39="", "MISSING", "OK") -> OK | C39: Megan Franklin | D39: 38 | E39: =IF(OR(D39<18, D39>100),AD38,D39) -> 38 | F39: Female | G39: =IF(F39="", "Unknown", IF(OR(F39="F", F39="FEMALE", F39="Female"), "Female", IF(OR(F39="M", F39="MALE", F39="Male"), "Male", "Other"))) -> Female | H39: Mombasa | I39: Business Owner | K39: =IF(I39="", "Unknown", I39) -> Business Owner | L39: 10 | M39: 2287359 | N39: =IF(OR(M39="",M39<0),$AD$3,M39) -> 2287359 | O39: 550875 | P39: 12.73 | Q39: 36 | R39: Personal | S39: =IF(R39="", "Unknown", R39) -> Personal | T39: 714 | U39: =IF(OR(T39="",T39>999),$AD$2,T39) -> 714 | V39: 6 | W39: Late (31-60 days) | X39: 2022-09-02 | Y39: =IF(ISNUMBER(X39), X39, DATEVALUE(X39)) -> 44806 | Z39: 0.2408
A40: LN-00043 | B40: =IF(A40="", "MISSING", "OK") -> OK | C40: Timothy Jacobson | D40: 24 | E40: =IF(OR(D40<18, D40>100),AD39,D40) -> 24 | F40: Male | G40: =IF(F40="", "Unknown", IF(OR(F40="F", F40="FEMALE", F40="Female"), "Female", IF(OR(F40="M", F40="MALE", F40="Male"), "Male", "Other"))) -> Male | H40: Mombasa | I40: Unemployed | K40: =IF(I40="", "Unknown", I40) -> Unemployed | L40: 16 | M40: 228874 | N40: =IF(OR(M40="",M40<0),$AD$3,M40) -> 228874 | O40: 289160 | P40: 12.15 | Q40: 36 | S40: =IF(R40="", "Unknown", R40) -> Unknown | T40: 460 | U40: =IF(OR(T40="",T40>999),$AD$2,T40) -> 460 | V40: 5 | W40: Late (61-90 days) | X40: 2022-02-17 | Y40: =IF(ISNUMBER(X40), X40, DATEVALUE(X40)) -> 44609 | Z40: 1.2634
A41: LN-00261 | B41: =IF(A41="", "MISSING", "OK") -> OK | C41: Jessica Ramsey | D41: 29 | E41: =IF(OR(D41<18, D41>100),AD40,D41) -> 29 | F41: Male | G41: =IF(F41="", "Unknown", IF(OR(F41="F", F41="FEMALE", F41="Female"), "Female", IF(OR(F41="M", F41="MALE", F41="Male"), "Male", "Other"))) -> Male | H41: Kisumu | I41: Business Owner | K41: =IF(I41="", "Unknown", I41) -> Business Owner | L41: 20 | M41: 1437949 | N41: =IF(OR(M41="",M41<0),$AD$3,M41) -> 1437949 | O41: 400596 | P41: 19.01 | Q41: 48 | R41: Agriculture | S41: =IF(R41="", "Unknown", R41) -> Agriculture | T41: 652 | U41: =IF(OR(T41="",T41>999),$AD$2,T41) -> 652 | V41: 7 | W41: Default | X41: 2022-05-17 | Y41: =IF(ISNUMBER(X41), X41, DATEVALUE(X41)) -> 44698 | Z41: 0.2786
A42: LN-00058 | B42: =IF(A42="", "MISSING", "OK") -> OK | C42: Jade Miles | D42: 60 | E42: =IF(OR(D42<18, D42>100),AD41,D42) -> 60 | F42: Male | G42: =IF(F42="", "Unknown", IF(OR(F42="F", F42="FEMALE", F42="Female"), "Female", IF(OR(F42="M", F42="MALE", F42="Male"), "Male", "Other"))) -> Male | H42: Eldoret | I42: Business Owner | K42: =IF(I42="", "Unknown", I42) -> Business Owner | L42: 0 | M42: 1396959 | N42: =IF(OR(M42="",M42<0),$AD$3,M42) -> 1396959 | O42: 388266 | P42: 8.61 | Q42: 48 | R42: Education | S42: =IF(R42="", "Unknown", R42) -> Education | T42: 691 | U42: =IF(OR(T42="",T42>999),$AD$2,T42) -> 691 | V42: 4 | W42: Default | X42: 2023-06-20 | Y42: =IF(ISNUMBER(X42), X42, DATEVALUE(X42)) -> 45097 | Z42: 0.2779
A43: LN-00982 | B43: =IF(A43="", "MISSING", "OK") -> OK | C43: Crystal Ramos | D43: 38 | E43: =IF(OR(D43<18, D43>100),AD42,D43) -> 38 | F43: Male | G43: =IF(F43="", "Unknown", IF(OR(F43="F", F43="FEMALE", F43="Female"), "Female", IF(OR(F43="M", F43="MALE", F43="Male"), "Male", "Other"))) -> Male | H43: Kisumu | I43: Self-Employed | K43: =IF(I43="", "Unknown", I43) -> Self-Employed | L43: 10 | M43: 1277353 | N43: =IF(OR(M43="",M43<0),$AD$3,M43) -> 1277353 | O43: 35534 | P43: 27.53 | Q43: 36 | R43: Home Improvement | S43: =IF(R43="", "Unknown", R43) -> Home Improvement | T43: 388 | U43: =IF(OR(T43="",T43>999),$AD$2,T43) -> 388 | V43: 7 | W43: Default | X43: 2023-05-01 | Y43: =IF(ISNUMBER(X43), X43, DATEVALUE(X43)) -> 45047 | Z43: 0.0278
A44: LN-00603 | B44: =IF(A44="", "MISSING", "OK") -> OK | C44: Amanda Smith | D44: 59 | E44: =IF(OR(D44<18, D44>100),AD43,D44) -> 59 | G44: =IF(F44="", "Unknown", IF(OR(F44="F", F44="FEMALE", F44="Female"), "Female", IF(OR(F44="M", F44="MALE", F44="Male"), "Male", "Other"))) -> Unknown | H44: Nyeri | I44: Self-Employed | K44: =IF(I44="", "Unknown", I44) -> Self-Employed | L44: 2 | M44: 1710891 | N44: =IF(OR(M44="",M44<0),$AD$3,M44) -> 1710891 | O44: 492963 | P44: 20.34 | Q44: 60 | R44: Agriculture | S44: =IF(R44="", "Unknown", R44) -> Agriculture | T44: 477 | U44: =IF(OR(T44="",T44>999),$AD$2,T44) -> 477 | V44: 5 | W44: Fully Paid | X44: 2022-02-25 | Y44: =IF(ISNUMBER(X44), X44, DATEVALUE(X44)) -> 44617 | Z44: 0.2881
A45: LN-00839 | B45: =IF(A45="", "MISSING", "OK") -> OK | C45: Thomas Willis | D45: 45 | E45: =IF(OR(D45<18, D45>100),AD44,D45) -> 45 | F45: Male | G45: =IF(F45="", "Unknown", IF(OR(F45="F", F45="FEMALE", F45="Female"), "Female", IF(OR(F45="M", F45="MALE", F45="Male"), "Male", "Other"))) -> Male | H45: Eldoret | I45: Business Owner | K45: =IF(I45="", "Unknown", I45) -> Business Owner | L45: 11 | M45: 1762460 | N45: =IF(OR(M45="",M45<0),$AD$3,M45) -> 1762460 | O45: 718876 | P45: 13.61 | Q45: 36 | R45: Education | S45: =IF(R45="", "Unknown", R45) -> Education | T45: 645 | U45: =IF(OR(T45="",T45>999),$AD$2,T45) -> 645 | V45: 4 | W45: Default | X45: 2021-07-26 | Y45: =IF(ISNUMBER(X45), X45, DATEVALUE(X45)) -> 44403 | Z45: 0.4079
A46: LN-00566 | B46: =IF(A46="", "MISSING", "OK") -> OK | C46: Maria Taylor | D46: 31 | E46: =IF(OR(D46<18, D46>100),AD45,D46) -> 31 | F46: Female | G46: =IF(F46="", "Unknown", IF(OR(F46="F", F46="FEMALE", F46="Female"), "Female", IF(OR(F46="M", F46="MALE", F46="Male"), "Male", "Other"))) -> Female | H46: Nairobi | I46: Business Owner | K46: =IF(I46="", "Unknown", I46) -> Business Owner | L46: 27 | M46: 1763246 | N46: =IF(OR(M46="",M46<0),$AD$3,M46) -> 1763246 | O46: 529565 | P46: 18.98 | Q46: 12 | R46: Agriculture | S46: =IF(R46="", "Unknown", R46) -> Agriculture | T46: 821 | U46: =IF(OR(T46="",T46>999),$AD$2,T46) -> 821 | V46: 2 | W46: Late (31-60 days) | X46: 2023-09-02 | Y46: =IF(ISNUMBER(X46), X46, DATEVALUE(X46)) -> 45171 | Z46: 0.3003
A47: LN-00645 | B47: =IF(A47="", "MISSING", "OK") -> OK | C47: Jasmine Villa | D47: 28 | E47: =IF(OR(D47<18, D47>100),AD46,D47) -> 28 | F47: Female | G47: =IF(F47="", "Unknown", IF(OR(F47="F", F47="FEMALE", F47="Female"), "Female", IF(OR(F47="M", F47="MALE", F47="Male"), "Male", "Other"))) -> Female | H47: Nyeri | I47: Employed | K47: =IF(I47="", "Unknown", I47) -> Employed | L47: 13 | M47: 1852717 | N47: =IF(OR(M47="",M47<0),$AD$3,M47) -> 1852717 | O47: 170653 | P47: 15.92 | Q47: 24 | R47: Medical | S47: =IF(R47="", "Unknown", R47) -> Medical | T47: 629 | U47: =IF(OR(T47="",T47>999),$AD$2,T47) -> 629 | V47: 4 | W47: Default | X47: 2023-07-07 | Y47: =IF(ISNUMBER(X47), X47, DATEVALUE(X47)) -> 45114 | Z47: 0.0921
A48: LN-00283 | B48: =IF(A48="", "MISSING", "OK") -> OK | C48: Anita Frey | D48: 38 | E48: =IF(OR(D48<18, D48>100),AD47,D48) -> 38 | F48: Male | G48: =IF(F48="", "Unknown", IF(OR(F48="F", F48="FEMALE", F48="Female"), "Female", IF(OR(F48="M", F48="MALE", F48="Male"), "Male", "Other"))) -> Male | H48: Mombasa | I48: Unemployed | K48: =IF(I48="", "Unknown", I48) -> Unemployed | L48: 8 | M48: 1222377 | N48: =IF(OR(M48="",M48<0),$AD$3,M48) -> 1222377 | O48: 752081 | P48: 12.63% | Q48: 60 | R48: Medical | S48: =IF(R48="", "Unknown", R48) -> Medical | T48: 625 | U48: =IF(OR(T48="",T48>999),$AD$2,T48) -> 625 | V48: 1 | W48: Late (31-60 days) | X48: 2021-05-26 | Y48: =IF(ISNUMBER(X48), X48, DATEVALUE(X48)) -> 44342 | Z48: 0.6153
A49: LN-01484 | B49: =IF(A49="", "MISSING", "OK") -> OK | C49: Charles Young | D49: 23 | E49: =IF(OR(D49<18, D49>100),AD48,D49) -> 23 | F49: Male | G49: =IF(F49="", "Unknown", IF(OR(F49="F", F49="FEMALE", F49="Female"), "Female", IF(OR(F49="M", F49="MALE", F49="Male"), "Male", "Other"))) -> Male | H49: Nyeri | I49: Business Owner | K49: =IF(I49="", "Unknown", I49) -> Business Owner | L49: 5 | M49: 339292 | N49: =IF(OR(M49="",M49<0),$AD$3,M49) -> 339292 | O49: 773890 | P49: 9.5 | Q49: 36 | R49: Personal | S49: =IF(R49="", "Unknown", R49) -> Personal | T49: 560 | U49: =IF(OR(T49="",T49>999),$AD$2,T49) -> 560 | V49: 4 | W49: Charged Off | X49: 2022-11-17 | Y49: =IF(ISNUMBER(X49), X49, DATEVALUE(X49)) -> 44882 | Z49: 2.2809
A50: LN-01399 | B50: =IF(A50="", "MISSING", "OK") -> OK | C50: Michele Pennington | D50: 64 | E50: =IF(OR(D50<18, D50>100),AD49,D50) -> 64 | F50: Male | G50: =IF(F50="", "Unknown", IF(OR(F50="F", F50="FEMALE", F50="Female"), "Female", IF(OR(F50="M", F50="MALE", F50="Male"), "Male", "Other"))) -> Male | H50: Machakos | I50: Business Owner | K50: =IF(I50="", "Unknown", I50) -> Business Owner | L50: 21 | M50: 968140 | N50: =IF(OR(M50="",M50<0),$AD$3,M50) -> 968140 | O50: 777634 | P50: 25.95 | Q50: 12 | R50: Medical | S50: =IF(R50="", "Unknown", R50) -> Medical | T50: 686 | U50: =IF(OR(T50="",T50>999),$AD$2,T50) -> 686 | V50: 2 | W50: Charged Off | X50: 2022-07-18 | Y50: =IF(ISNUMBER(X50), X50, DATEVALUE(X50)) -> 44760 | Z50: 0.8032
A51: LN-01197 | B51: =IF(A51="", "MISSING", "OK") -> OK | C51: Alexandra George | D51: 51 | E51: =IF(OR(D51<18, D51>100),AD50,D51) -> 51 | F51: FEMALE | G51: =IF(F51="", "Unknown", IF(OR(F51="F", F51="FEMALE", F51="Female"), "Female", IF(OR(F51="M", F51="MALE", F51="Male"), "Male", "Other"))) -> Female | H51: Machakos | I51: Self-Employed | K51: =IF(I51="", "Unknown", I51) -> Self-Employed | L51: 11 | M51: 1736396 | N51: =IF(OR(M51="",M51<0),$AD$3,M51) -> 1736396 | O51: 367823 | P51: 13.95 | Q51: 60 | R51: Education | S51: =IF(R51="", "Unknown", R51) -> Education | T51: 358 | U51: =IF(OR(T51="",T51>999),$AD$2,T51) -> 358 | V51: 4 | W51: Late (61-90 days) | X51: 2022-08-19 | Y51: =IF(ISNUMBER(X51), X51, DATEVALUE(X51)) -> 44792 | Z51: 0.2118
A52: LN-00961 | B52: =IF(A52="", "MISSING", "OK") -> OK | C52: Phillip Velazquez | D52: 21 | E52: =IF(OR(D52<18, D52>100),AD51,D52) -> 21 | F52: Female | G52: =IF(F52="", "Unknown", IF(OR(F52="F", F52="FEMALE", F52="Female"), "Female", IF(OR(F52="M", F52="MALE", F52="Male"), "Male", "Other"))) -> Female | H52: Kisumu | I52: Business Owner | K52: =IF(I52="", "Unknown", I52) -> Business Owner | L52: 28 | M52: 868725 | N52: =IF(OR(M52="",M52<0),$AD$3,M52) -> 868725 | O52: 323602 | P52: 21.58 | Q52: 24 | R52: Agriculture | S52: =IF(R52="", "Unknown", R52) -> Agriculture | T52: 375 | U52: =IF(OR(T52="",T52>999),$AD$2,T52) -> 375 | V52: 3 | W52: Charged Off | X52: 2023-03-10 | Y52: =IF(ISNUMBER(X52), X52, DATEVALUE(X52)) -> 44995 | Z52: 0.3725
A53: LN-00254 | B53: =IF(A53="", "MISSING", "OK") -> OK | C53: Mary Willis | D53: 46 | E53: =IF(OR(D53<18, D53>100),AD52,D53) -> 46 | F53: Female | G53: =IF(F53="", "Unknown", IF(OR(F53="F", F53="FEMALE", F53="Female"), "Female", IF(OR(F53="M", F53="MALE", F53="Male"), "Male", "Other"))) -> Female | H53: Nyeri | I53: Self-Employed | K53: =IF(I53="", "Unknown", I53) -> Self-Employed | L53: 21 | M53: 2158281 | N53: =IF(OR(M53="",M53<0),$AD$3,M53) -> 2158281 | O53: 784265 | P53: 16.35 | Q53: 60 | R53: Education | S53: =IF(R53="", "Unknown", R53) -> Education | T53: 751 | U53: =IF(OR(T53="",T53>999),$AD$2,T53) -> 751 | V53: 1 | W53: Late (31-60 days) | X53: 2022-04-13 | Y53: =IF(ISNUMBER(X53), X53, DATEVALUE(X53)) -> 44664 | Z53: 0.3634
A54: LN-00262 | B54: =IF(A54="", "MISSING", "OK") -> OK | C54: Jacqueline Terry | D54: 61 | E54: =IF(OR(D54<18, D54>100),AD53,D54) -> 61 | F54: Male | G54: =IF(F54="", "Unknown", IF(OR(F54="F", F54="FEMALE", F54="Female"), "Female", IF(OR(F54="M", F54="MALE", F54="Male"), "Male", "Other"))) -> Male | H54: Nyeri | I54: Employed | K54: =IF(I54="", "Unknown", I54) -> Employed | L54: 5 | N54: =IF(OR(M54="",M54<0),$AD$3,M54) -> 1333224 | O54: 731111 | P54: 16.06 | Q54: 24 | R54: Medical | S54: =IF(R54="", "Unknown", R54) -> Medical | U54: =IF(OR(T54="",T54>999),$AD$2,T54) -> 556 | V54: 1 | W54: Charged Off | X54: 2022-04-21 | Y54: =IF(ISNUMBER(X54), X54, DATEVALUE(X54)) -> 44672 | Z54: 0.6068
A55: LN-00569 | B55: =IF(A55="", "MISSING", "OK") -> OK | C55: Dr. William Mack | D55: 29 | E55: =IF(OR(D55<18, D55>100),AD54,D55) -> 29 | F55: Male | G55: =IF(F55="", "Unknown", IF(OR(F55="F", F55="FEMALE", F55="Female"), "Female", IF(OR(F55="M", F55="MALE", F55="Male"), "Male", "Other"))) -> Male | H55: Nakuru | I55: Business Owner | K55: =IF(I55="", "Unknown", I55) -> Business Owner | L55: 10 | M55: 2339081 | N55: =IF(OR(M55="",M55<0),$AD$3,M55) -> 2339081 | O55: 433089 | P55: 15.77 | Q55: 48 | R55: Personal | S55: =IF(R55="", "Unknown", R55) -> Personal | T55: 841 | U55: =IF(OR(T55="",T55>999),$AD$2,T55) -> 841 | V55: 2 | W55: Fully Paid | X55: 2022-06-23 | Y55: =IF(ISNUMBER(X55), X55, DATEVALUE(X55)) -> 44735 | Z55: 0.1852
A56: LN-01443 | B56: =IF(A56="", "MISSING", "OK") -> OK | C56: Victoria Smith | D56: 45 | E56: =IF(OR(D56<18, D56>100),AD55,D56) -> 45 | F56: Male | G56: =IF(F56="", "Unknown", IF(OR(F56="F", F56="FEMALE", F56="Female"), "Female", IF(OR(F56="M", F56="MALE", F56="Male"), "Male", "Other"))) -> Male | H56: Mombasa | I56: Unemployed | K56: =IF(I56="", "Unknown", I56) -> Unemployed | L56: 13 | M56: 397770 | N56: =IF(OR(M56="",M56<0),$AD$3,M56) -> 397770 | O56: 498454 | P56: 26.45 | Q56: 60 | R56: Agriculture | S56: =IF(R56="", "Unknown", R56) -> Agriculture | T56: 500 | U56: =IF(OR(T56="",T56>999),$AD$2,T56) -> 500 | V56: 2 | W56: Fully Paid | X56: 2021-05-13 | Y56: =IF(ISNUMBER(X56), X56, DATEVALUE(X56)) -> 44329 | Z56: 1.2531
A57: LN-00807 | B57: =IF(A57="", "MISSING", "OK") -> OK | C57: Leslie Long | D57: 46 | E57: =IF(OR(D57<18, D57>100),AD56,D57) -> 46 | F57: Male | G57: =IF(F57="", "Unknown", IF(OR(F57="F", F57="FEMALE", F57="Female"), "Female", IF(OR(F57="M", F57="MALE", F57="Male"), "Male", "Other"))) -> Male | H57: Eldoret | I57: Unemployed | K57: =IF(I57="", "Unknown", I57) -> Unemployed | L57: 2 | M57: 209725 | N57: =IF(OR(M57="",M57<0),$AD$3,M57) -> 209725 | O57: 80128 | P57: 15.16 | Q57: 48 | R57: Medical | S57: =IF(R57="", "Unknown", R57) -> Medical | T57: 664 | U57: =IF(OR(T57="",T57>999),$AD$2,T57) -> 664 | V57: 5 | W57: Late (31-60 days) | X57: 2020-12-26 | Y57: =IF(ISNUMBER(X57), X57, DATEVALUE(X57)) -> 44191 | Z57: 0.3821
A58: LN-00420 | B58: =IF(A58="", "MISSING", "OK") -> OK | C58: Bill Forbes | D58: 45 | E58: =IF(OR(D58<18, D58>100),AD57,D58) -> 45 | F58: Female | G58: =IF(F58="", "Unknown", IF(OR(F58="F", F58="FEMALE", F58="Female"), "Female", IF(OR(F58="M", F58="MALE", F58="Male"), "Male", "Other"))) -> Female | H58: Kakamega | I58: Self-Employed | K58: =IF(I58="", "Unknown", I58) -> Self-Employed | L58: 2 | M58: 885475 | N58: =IF(OR(M58="",M58<0),$AD$3,M58) -> 885475 | O58: 325505 | P58: 25.72 | Q58: 24 | R58: Education | S58: =IF(R58="", "Unknown", R58) -> Education | T58: 703 | U58: =IF(OR(T58="",T58>999),$AD$2,T58) -> 703 | V58: 2 | W58: Late (31-60 days) | X58: 2020-03-31 | Y58: =IF(ISNUMBER(X58), X58, DATEVALUE(X58)) -> 43921 | Z58: 0.3676
A59: LN-01431 | B59: =IF(A59="", "MISSING", "OK") -> OK | C59: Teresa Smith | D59: 45 | E59: =IF(OR(D59<18, D59>100),AD58,D59) -> 45 | F59: Male | G59: =IF(F59="", "Unknown", IF(OR(F59="F", F59="FEMALE", F59="Female"), "Female", IF(OR(F59="M", F59="MALE", F59="Male"), "Male", "Other"))) -> Male | H59: Kisumu | I59: Self-Employed | K59: =IF(I59="", "Unknown", I59) -> Self-Employed | L59: 0 | M59: 1202892 | N59: =IF(OR(M59="",M59<0),$AD$3,M59) -> 1202892 | O59: 154445 | P59: 9.06 | Q59: 36 | R59: Medical | S59: =IF(R59="", "Unknown", R59) -> Medical | T59: 472 | U59: =IF(OR(T59="",T59>999),$AD$2,T59) -> 472 | V59: 3 | W59: Current | X59: 2021-01-23 | Y59: =IF(ISNUMBER(X59), X59, DATEVALUE(X59)) -> 44219 | Z59: 0.1284
A60: LN-00890 | B60: =IF(A60="", "MISSING", "OK") -> OK | C60: Brian Duffy | D60: 56 | E60: =IF(OR(D60<18, D60>100),AD59,D60) -> 56 | F60: Male | G60: =IF(F60="", "Unknown", IF(OR(F60="F", F60="FEMALE", F60="Female"), "Female", IF(OR(F60="M", F60="MALE", F60="Male"), "Male", "Other"))) -> Male | H60: Machakos | I60: Unemployed | K60: =IF(I60="", "Unknown", I60) -> Unemployed | L60: 13 | M60: 1275426 | N60: =IF(OR(M60="",M60<0),$AD$3,M60) -> 1275426 | O60: 448745 | P60: 8.5 | Q60: 12 | R60: Medical | S60: =IF(R60="", "Unknown", R60) -> Medical | T60: 353 | U60: =IF(OR(T60="",T60>999),$AD$2,T60) -> 353 | V60: 5 | W60: Default | X60: 2021-01-14 | Y60: =IF(ISNUMBER(X60), X60, DATEVALUE(X60)) -> 44210 | Z60: 0.3518
A61: LN-01161 | B61: =IF(A61="", "MISSING", "OK") -> OK | C61: Ryan Kelly | D61: 59 | E61: =IF(OR(D61<18, D61>100),AD60,D61) -> 59 | F61: Female | G61: =IF(F61="", "Unknown", IF(OR(F61="F", F61="FEMALE", F61="Female"), "Female", IF(OR(F61="M", F61="MALE", F61="Male"), "Male", "Other"))) -> Female | H61: Machakos | I61: Self-Employed | K61: =IF(I61="", "Unknown", I61) -> Self-Employed | L61: 17 | M61: 465711 | N61: =IF(OR(M61="",M61<0),$AD$3,M61) -> 465711 | O61: 444671 | P61: 23.56 | Q61: 12 | R61: Business | S61: =IF(R61="", "Unknown", R61) -> Business | T61: 760 | U61: =IF(OR(T61="",T61>999),$AD$2,T61) -> 760 | V61: 5 | W61: Late (31-60 days) | X61: 2022-02-11 | Y61: =IF(ISNUMBER(X61), X61, DATEVALUE(X61)) -> 44603 | Z61: 0.9548
A62: LN-00687 | B62: =IF(A62="", "MISSING", "OK") -> OK | C62: Brandon Salazar | D62: 47 | E62: =IF(OR(D62<18, D62>100),AD61,D62) -> 47 | F62: Female | G62: =IF(F62="", "Unknown", IF(OR(F62="F", F62="FEMALE", F62="Female"), "Female", IF(OR(F62="M", F62="MALE", F62="Male"), "Male", "Other"))) -> Female | H62: Kisumu | I62: Business Owner | K62: =IF(I62="", "Unknown", I62) -> Business Owner | L62: 6 | M62: 1281928 | N62: =IF(OR(M62="",M62<0),$AD$3,M62) -> 1281928 | O62: 45991 | P62: 9.17 | Q62: 12 | R62: Medical | S62: =IF(R62="", "Unknown", R62) -> Medical | T62: 346 | U62: =IF(OR(T62="",T62>999),$AD$2,T62) -> 346 | V62: 4 | W62: Charged Off | X62: 2023-01-07 | Y62: =IF(ISNUMBER(X62), X62, DATEVALUE(X62)) -> 44933 | Z62: 0.0359
A63: LN-01032 | B63: =IF(A63="", "MISSING", "OK") -> OK | C63: Hannah Johnson | D63: 44 | E63: =IF(OR(D63<18, D63>100),AD62,D63) -> 44 | F63: Male | G63: =IF(F63="", "Unknown", IF(OR(F63="F", F63="FEMALE", F63="Female"), "Female", IF(OR(F63="M", F63="MALE", F63="Male"), "Male", "Other"))) -> Male | H63: Eldoret | I63: Business Owner | K63: =IF(I63="", "Unknown", I63) -> Business Owner | L63: 2 | M63: 2048388 | N63: =IF(OR(M63="",M63<0),$AD$3,M63) -> 2048388 | O63: 256187 | P63: 20.91 | Q63: 24 | R63: Personal | S63: =IF(R63="", "Unknown", R63) -> Personal | T63: 741 | U63: =IF(OR(T63="",T63>999),$AD$2,T63) -> 741 | V63: 0 | W63: Late (61-90 days) | X63: 2023-05-21 | Y63: =IF(ISNUMBER(X63), X63, DATEVALUE(X63)) -> 45067 | Z63: 0.1251
A64: LN-00951 | B64: =IF(A64="", "MISSING", "OK") -> OK | C64: Stephen Mckinney | D64: 51 | E64: =IF(OR(D64<18, D64>100),AD63,D64) -> 51 | F64: FEMALE | G64: =IF(F64="", "Unknown", IF(OR(F64="F", F64="FEMALE", F64="Female"), "Female", IF(OR(F64="M", F64="MALE", F64="Male"), "Male", "Other"))) -> Female | H64: Nakuru | I64: Employed | K64: =IF(I64="", "Unknown", I64) -> Employed | L64: 18 | N64: =IF(OR(M64="",M64<0),$AD$3,M64) -> 1333224 | O64: 790644 | P64: 20.99 | Q64: 24 | R64: Medical | S64: =IF(R64="", "Unknown", R64) -> Medical | T64: 543 | U64: =IF(OR(T64="",T64>999),$AD$2,T64) -> 543 | V64: 6 | W64: Current | X64: 2023-06-20 | Y64: =IF(ISNUMBER(X64), X64, DATEVALUE(X64)) -> 45097 | Z64: 0.387
A65: LN-01170 | B65: =IF(A65="", "MISSING", "OK") -> OK | C65: Emma Miranda | D65: 48 | E65: =IF(OR(D65<18, D65>100),AD64,D65) -> 48 | F65: Male | G65: =IF(F65="", "Unknown", IF(OR(F65="F", F65="FEMALE", F65="Female"), "Female", IF(OR(F65="M", F65="MALE", F65="Male"), "Male", "Other"))) -> Male | H65: Nairobi | I65: Unemployed | K65: =IF(I65="", "Unknown", I65) -> Unemployed | L65: 20 | M65: 1156433 | N65: =IF(OR(M65="",M65<0),$AD$3,M65) -> 1156433 | O65: 707069 | P65: 25.15 | Q65: 36 | R65: Home Improvement | S65: =IF(R65="", "Unknown", R65) -> Home Improvement | T65: 469 | U65: =IF(OR(T65="",T65>999),$AD$2,T65) -> 469 | V65: 3 | W65: Late (31-60 days) | X65: 2022-04-21 | Y65: =IF(ISNUMBER(X65), X65, DATEVALUE(X65)) -> 44672 | Z65: 0.6114
A66: LN-00994 | B66: =IF(A66="", "MISSING", "OK") -> OK | C66: Matthew Daniels | D66: 45 | E66: =IF(OR(D66<18, D66>100),AD65,D66) -> 45 | F66: Female | G66: =IF(F66="", "Unknown", IF(OR(F66="F", F66="FEMALE", F66="Female"), "Female", IF(OR(F66="M", F66="MALE", F66="Male"), "Male", "Other"))) -> Female | H66: Kakamega | I66: Self-Employed | K66: =IF(I66="", "Unknown", I66) -> Self-Employed | L66: 21 | M66: 2271635 | N66: =IF(OR(M66="",M66<0),$AD$3,M66) -> 2271635 | O66: 731413 | P66: 19.5 | Q66: 36 | R66: Personal | S66: =IF(R66="", "Unknown", R66) -> Personal | T66: 413 | U66: =IF(OR(T66="",T66>999),$AD$2,T66) -> 413 | V66: 0 | W66: Default | X66: 2021-04-23 | Y66: =IF(ISNUMBER(X66), X66, DATEVALUE(X66)) -> 44309 | Z66: 0.322
A67: LN-00489 | B67: =IF(A67="", "MISSING", "OK") -> OK | C67: Brooke Cantu | D67: 22 | E67: =IF(OR(D67<18, D67>100),AD66,D67) -> 22 | F67: Female | G67: =IF(F67="", "Unknown", IF(OR(F67="F", F67="FEMALE", F67="Female"), "Female", IF(OR(F67="M", F67="MALE", F67="Male"), "Male", "Other"))) -> Female | H67: Eldoret | I67: Unemployed | K67: =IF(I67="", "Unknown", I67) -> Unemployed | L67: 16 | M67: 2234780 | N67: =IF(OR(M67="",M67<0),$AD$3,M67) -> 2234780 | O67: 69976 | P67: 9.2 | Q67: 48 | R67: Business | S67: =IF(R67="", "Unknown", R67) -> Business | T67: 831 | U67: =IF(OR(T67="",T67>999),$AD$2,T67) -> 831 | V67: 5 | W67: Fully Paid | X67: 2021-07-24 | Y67: =IF(ISNUMBER(X67), X67, DATEVALUE(X67)) -> 44401 | Z67: 0.0313
A68: LN-01353 | B68: =IF(A68="", "MISSING", "OK") -> OK | C68: Katherine Thompson | D68: 45 | E68: =IF(OR(D68<18, D68>100),AD67,D68) -> 45 | F68: Male | G68: =IF(F68="", "Unknown", IF(OR(F68="F", F68="FEMALE", F68="Female"), "Female", IF(OR(F68="M", F68="MALE", F68="Male"), "Male", "Other"))) -> Male | H68: Eldoret | I68: Employed | K68: =IF(I68="", "Unknown", I68) -> Employed | L68: 27 | M68: 1784642 | N68: =IF(OR(M68="",M68<0),$AD$3,M68) -> 1784642 | O68: 537039 | P68: 24.9 | Q68: 36 | R68: Business | S68: =IF(R68="", "Unknown", R68) -> Business | T68: 792 | U68: =IF(OR(T68="",T68>999),$AD$2,T68) -> 792 | V68: 5 | W68: Late (31-60 days) | X68: 2022-01-19 | Y68: =IF(ISNUMBER(X68), X68, DATEVALUE(X68)) -> 44580 | Z68: 0.3009
A69: LN-01166 | B69: =IF(A69="", "MISSING", "OK") -> OK | C69: John Smith | D69: 39 | E69: =IF(OR(D69<18, D69>100),AD68,D69) -> 39 | F69: Female | G69: =IF(F69="", "Unknown", IF(OR(F69="F", F69="FEMALE", F69="Female"), "Female", IF(OR(F69="M", F69="MALE", F69="Male"), "Male", "Other"))) -> Female | H69: Machakos | I69: Employed | K69: =IF(I69="", "Unknown", I69) -> Employed | L69: 22 | M69: 2205739 | N69: =IF(OR(M69="",M69<0),$AD$3,M69) -> 2205739 | O69: 204514 | P69: 23.09 | Q69: 12 | R69: Medical | S69: =IF(R69="", "Unknown", R69) -> Medical | T69: 301 | U69: =IF(OR(T69="",T69>999),$AD$2,T69) -> 301 | V69: 4 | W69: Late (61-90 days) | X69: 2021-05-04 | Y69: =IF(ISNUMBER(X69), X69, DATEVALUE(X69)) -> 44320 | Z69: 0.0927
A70: LN-00286 | B70: =IF(A70="", "MISSING", "OK") -> OK | C70: Anthony Mcclain DVM | D70: 36 | E70: =IF(OR(D70<18, D70>100),AD69,D70) -> 36 | F70: Female | G70: =IF(F70="", "Unknown", IF(OR(F70="F", F70="FEMALE", F70="Female"), "Female", IF(OR(F70="M", F70="MALE", F70="Male"), "Male", "Other"))) -> Female | H70: Kisumu | I70: Self-Employed | K70: =IF(I70="", "Unknown", I70) -> Self-Employed | L70: 14 | M70: 1248392 | N70: =IF(OR(M70="",M70<0),$AD$3,M70) -> 1248392 | O70: 457985 | P70: 27.16 | Q70: 12 | R70: Home Improvement | S70: =IF(R70="", "Unknown", R70) -> Home Improvement | T70: 623 | U70: =IF(OR(T70="",T70>999),$AD$2,T70) -> 623 | V70: 5 | W70: Charged Off | X70: 2023-02-01 | Y70: =IF(ISNUMBER(X70), X70, DATEVALUE(X70)) -> 44958 | Z70: 0.3669
A71: LN-01159 | B71: =IF(A71="", "MISSING", "OK") -> OK | C71: Michael Adams Jr. | D71: 28 | E71: =IF(OR(D71<18, D71>100),AD70,D71) -> 28 | F71: Male | G71: =IF(F71="", "Unknown", IF(OR(F71="F", F71="FEMALE", F71="Female"), "Female", IF(OR(F71="M", F71="MALE", F71="Male"), "Male", "Other"))) -> Male | H71: Mombasa | I71: Business Owner | K71: =IF(I71="", "Unknown", I71) -> Business Owner | L71: 16 | M71: 2104717 | N71: =IF(OR(M71="",M71<0),$AD$3,M71) -> 2104717 | O71: 393393 | P71: 25.32 | Q71: 48 | R71: Business | S71: =IF(R71="", "Unknown", R71) -> Business | T71: 621 | U71: =IF(OR(T71="",T71>999),$AD$2,T71) -> 621 | V71: 6 | W71: Late (31-60 days) | X71: 2023-02-04 | Y71: =IF(ISNUMBER(X71), X71, DATEVALUE(X71)) -> 44961 | Z71: 0.1869
A72: LN-01306 | B72: =IF(A72="", "MISSING", "OK") -> OK | C72: Joshua Perry | D72: 39 | E72: =IF(OR(D72<18, D72>100),AD71,D72) -> 39 | F72: Female | G72: =IF(F72="", "Unknown", IF(OR(F72="F", F72="FEMALE", F72="Female"), "Female", IF(OR(F72="M", F72="MALE", F72="Male"), "Male", "Other"))) -> Female | H72: Kisumu | I72: Unemployed | K72: =IF(I72="", "Unknown", I72) -> Unemployed | L72: 27 | M72: 1214262 | N72: =IF(OR(M72="",M72<0),$AD$3,M72) -> 1214262 | O72: 79821 | P72: 10.46 | Q72: 24 | R72: Agriculture | S72: =IF(R72="", "Unknown", R72) -> Agriculture | U72: =IF(OR(T72="",T72>999),$AD$2,T72) -> 556 | V72: 7 | W72: Late (61-90 days) | X72: 2021-12-22 | Y72: =IF(ISNUMBER(X72), X72, DATEVALUE(X72)) -> 44552 | Z72: 0.0657
A73: LN-01361 | B73: =IF(A73="", "MISSING", "OK") -> OK | C73: Aaron Flowers | D73: 52 | E73: =IF(OR(D73<18, D73>100),AD72,D73) -> 52 | F73: Female | G73: =IF(F73="", "Unknown", IF(OR(F73="F", F73="FEMALE", F73="Female"), "Female", IF(OR(F73="M", F73="MALE", F73="Male"), "Male", "Other"))) -> Female | H73: Thika | I73: Self-Employed | K73: =IF(I73="", "Unknown", I73) -> Self-Employed | L73: 13 | M73: 347647 | N73: =IF(OR(M73="",M73<0),$AD$3,M73) -> 347647 | O73: 718148 | P73: 20.69 | Q73: 60 | R73: Agriculture | S73: =IF(R73="", "Unknown", R73) -> Agriculture | T73: 680 | U73: =IF(OR(T73="",T73>999),$AD$2,T73) -> 680 | V73: 0 | W73: Current | X73: 2022-01-24 | Y73: =IF(ISNUMBER(X73), X73, DATEVALUE(X73)) -> 44585 | Z73: 2.0657
A74: LN-01301 | B74: =IF(A74="", "MISSING", "OK") -> OK | C74: Michael Little | D74: 42 | E74: =IF(OR(D74<18, D74>100),AD73,D74) -> 42 | F74: Male | G74: =IF(F74="", "Unknown", IF(OR(F74="F", F74="FEMALE", F74="Female"), "Female", IF(OR(F74="M", F74="MALE", F74="Male"), "Male", "Other"))) -> Male | H74: Nakuru | I74: Employed | K74: =IF(I74="", "Unknown", I74) -> Employed | L74: 22 | M74: 2115135 | N74: =IF(OR(M74="",M74<0),$AD$3,M74) -> 2115135 | O74: 475061 | P74: 13.96 | Q74: 36 | R74: Personal | S74: =IF(R74="", "Unknown", R74) -> Personal | T74: 827 | U74: =IF(OR(T74="",T74>999),$AD$2,T74) -> 827 | V74: 2 | W74: Late (61-90 days) | X74: 2023-05-26 | Y74: =IF(ISNUMBER(X74), X74, DATEVALUE(X74)) -> 45072 | Z74: 0.2246
A75: LN-00526 | B75: =IF(A75="", "MISSING", "OK") -> OK | C75: Kaitlin Owens | D75: 45 | E75: =IF(OR(D75<18, D75>100),AD74,D75) -> 45 | F75: Male | G75: =IF(F75="", "Unknown", IF(OR(F75="F", F75="FEMALE", F75="Female"), "Female", IF(OR(F75="M", F75="MALE", F75="Male"), "Male", "Other"))) -> Male | H75: Machakos | I75: Unemployed | K75: =IF(I75="", "Unknown", I75) -> Unemployed | L75: 18 | M75: 1460617 | N75: =IF(OR(M75="",M75<0),$AD$3,M75) -> 1460617 | O75: 156213 | P75: 21.96 | Q75: 24 | R75: Business | S75: =IF(R75="", "Unknown", R75) -> Business | T75: 819 | U75: =IF(OR(T75="",T75>999),$AD$2,T75) -> 819 | V75: 6 | W75: Default | X75: 2023-10-05 | Y75: =IF(ISNUMBER(X75), X75, DATEVALUE(X75)) -> 45204 | Z75: 0.107
A76: LN-00543 | B76: =IF(A76="", "MISSING", "OK") -> OK | C76: Adam Trujillo | D76: 48 | E76: =IF(OR(D76<18, D76>100),AD75,D76) -> 48 | F76: Female | G76: =IF(F76="", "Unknown", IF(OR(F76="F", F76="FEMALE", F76="Female"), "Female", IF(OR(F76="M", F76="MALE", F76="Male"), "Male", "Other"))) -> Female | H76: Eldoret | I76: Business Owner | K76: =IF(I76="", "Unknown", I76) -> Business Owner | L76: 29 | M76: 1087669 | N76: =IF(OR(M76="",M76<0),$AD$3,M76) -> 1087669 | O76: 89087 | P76: 19.13 | Q76: 12 | R76: Medical | S76: =IF(R76="", "Unknown", R76) -> Medical | T76: 642 | U76: =IF(OR(T76="",T76>999),$AD$2,T76) -> 642 | V76: 4 | W76: Current | X76: 2022-04-04 | Y76: =IF(ISNUMBER(X76), X76, DATEVALUE(X76)) -> 44655 | Z76: 0.0819
A77: LN-00579 | B77: =IF(A77="", "MISSING", "OK") -> OK | C77: Erica Curry | D77: 47 | E77: =IF(OR(D77<18, D77>100),AD76,D77) -> 47 | F77: Female | G77: =IF(F77="", "Unknown", IF(OR(F77="F", F77="FEMALE", F77="Female"), "Female", IF(OR(F77="M", F77="MALE", F77="Male"), "Male", "Other"))) -> Female | H77: Nairobi | I77: Business Owner | K77: =IF(I77="", "Unknown", I77) -> Business Owner | L77: 14 | M77: 1793325 | N77: =IF(OR(M77="",M77<0),$AD$3,M77) -> 1793325 | O77: 414754 | P77: 27.91 | Q77: 24 | R77: Education | S77: =IF(R77="", "Unknown", R77) -> Education | T77: 514 | U77: =IF(OR(T77="",T77>999),$AD$2,T77) -> 514 | V77: 6 | W77: Default | X77: 2022-11-21 | Y77: =IF(ISNUMBER(X77), X77, DATEVALUE(X77)) -> 44886 | Z77: 0.2313
A78: LN-00671 | B78: =IF(A78="", "MISSING", "OK") -> OK | C78: Michael Scott | D78: 38 | E78: =IF(OR(D78<18, D78>100),AD77,D78) -> 38 | F78: Female | G78: =IF(F78="", "Unknown", IF(OR(F78="F", F78="FEMALE", F78="Female"), "Female", IF(OR(F78="M", F78="MALE", F78="Male"), "Male", "Other"))) -> Female | H78: Nyeri | I78: Business Owner | K78: =IF(I78="", "Unknown", I78) -> Business Owner | L78: 19 | M78: 1513140 | N78: =IF(OR(M78="",M78<0),$AD$3,M78) -> 1513140 | O78: 517952 | P78: 9.23 | Q78: 24 | R78: Personal | S78: =IF(R78="", "Unknown", R78) -> Personal | T78: 552 | U78: =IF(OR(T78="",T78>999),$AD$2,T78) -> 552 | V78: 5 | W78: Late (61-90 days) | X78: 2022-05-01 | Y78: =IF(ISNUMBER(X78), X78, DATEVALUE(X78)) -> 44682 | Z78: 0.3423
A79: LN-01103 | B79: =IF(A79="", "MISSING", "OK") -> OK | C79: Ms. Nicole Hahn DDS | D79: 46 | E79: =IF(OR(D79<18, D79>100),AD78,D79) -> 46 | F79: Male | G79: =IF(F79="", "Unknown", IF(OR(F79="F", F79="FEMALE", F79="Female"), "Female", IF(OR(F79="M", F79="MALE", F79="Male"), "Male", "Other"))) -> Male | H79: Kakamega | I79: Business Owner | K79: =IF(I79="", "Unknown", I79) -> Business Owner | L79: 23 | M79: 1191316 | N79: =IF(OR(M79="",M79<0),$AD$3,M79) -> 1191316 | O79: 240283 | P79: 27.65 | Q79: 12 | R79: Home Improvement | S79: =IF(R79="", "Unknown", R79) -> Home Improvement | T79: 345 | U79: =IF(OR(T79="",T79>999),$AD$2,T79) -> 345 | V79: 1 | W79: Charged Off | X79: 2022-09-19 | Y79: =IF(ISNUMBER(X79), X79, DATEVALUE(X79)) -> 44823 | Z79: 0.2017
A80: LN-01379 | B80: =IF(A80="", "MISSING", "OK") -> OK | C80: Frank Gregory | D80: 51 | E80: =IF(OR(D80<18, D80>100),AD79,D80) -> 51 | F80: Male | G80: =IF(F80="", "Unknown", IF(OR(F80="F", F80="FEMALE", F80="Female"), "Female", IF(OR(F80="M", F80="MALE", F80="Male"), "Male", "Other"))) -> Male | H80: Kisumu | I80: Unemployed | K80: =IF(I80="", "Unknown", I80) -> Unemployed | L80: 23 | M80: 1686145 | N80: =IF(OR(M80="",M80<0),$AD$3,M80) -> 1686145 | O80: 55903 | P80: 16.93 | Q80: 60 | R80: Home Improvement | S80: =IF(R80="", "Unknown", R80) -> Home Improvement | T80: 396 | U80: =IF(OR(T80="",T80>999),$AD$2,T80) -> 396 | V80: 7 | W80: Late (31-60 days) | X80: 2023-08-19 | Y80: =IF(ISNUMBER(X80), X80, DATEVALUE(X80)) -> 45157 | Z80: 0.0332
A81: LN-00809 | B81: =IF(A81="", "MISSING", "OK") -> OK | C81: John Jackson | D81: 29 | E81: =IF(OR(D81<18, D81>100),AD80,D81) -> 29 | F81: Female | G81: =IF(F81="", "Unknown", IF(OR(F81="F", F81="FEMALE", F81="Female"), "Female", IF(OR(F81="M", F81="MALE", F81="Male"), "Male", "Other"))) -> Female | H81: Eldoret | I81: Unemployed | K81: =IF(I81="", "Unknown", I81) -> Unemployed | L81: 28 | M81: 284555 | N81: =IF(OR(M81="",M81<0),$AD$3,M81) -> 284555 | O81: 253540 | P81: 21.69 | Q81: 60 | R81: Home Improvement | S81: =IF(R81="", "Unknown", R81) -> Home Improvement | T81: 701 | U81: =IF(OR(T81="",T81>999),$AD$2,T81) -> 701 | V81: 2 | W81: Default | X81: 2023-08-25 | Y81: =IF(ISNUMBER(X81), X81, DATEVALUE(X81)) -> 45163 | Z81: 0.891
A82: LN-01403 | B82: =IF(A82="", "MISSING", "OK") -> OK | C82: Christina Carr | D82: 49 | E82: =IF(OR(D82<18, D82>100),AD81,D82) -> 49 | F82: Female | G82: =IF(F82="", "Unknown", IF(OR(F82="F", F82="FEMALE", F82="Female"), "Female", IF(OR(F82="M", F82="MALE", F82="Male"), "Male", "Other"))) -> Female | H82: Thika | I82: Self-Employed | K82: =IF(I82="", "Unknown", I82) -> Self-Employed | L82: 1 | M82: 711972 | N82: =IF(OR(M82="",M82<0),$AD$3,M82) -> 711972 | O82: 205639 | P82: 19.95 | Q82: 60 | R82: Business | S82: =IF(R82="", "Unknown", R82) -> Business | T82: -50 | U82: =IF(OR(T82="",T82>999),$AD$2,T82) -> -50 | V82: 5 | W82: Late (61-90 days) | X82: 2023-01-11 | Y82: =IF(ISNUMBER(X82), X82, DATEVALUE(X82)) -> 44937 | Z82: 0.2888
A83: LN-00708 | B83: =IF(A83="", "MISSING", "OK") -> OK | C83: Michael Rhodes | D83: 39 | E83: =IF(OR(D83<18, D83>100),AD82,D83) -> 39 | F83: Male | G83: =IF(F83="", "Unknown", IF(OR(F83="F", F83="FEMALE", F83="Female"), "Female", IF(OR(F83="M", F83="MALE", F83="Male"), "Male", "Other"))) -> Male | H83: Nyeri | I83: Unemployed | K83: =IF(I83="", "Unknown", I83) -> Unemployed | L83: 13 | M83: 2340682 | N83: =IF(OR(M83="",M83<0),$AD$3,M83) -> 2340682 | O83: 79778 | P83: 24.57 | Q83: 12 | R83: Personal | S83: =IF(R83="", "Unknown", R83) -> Personal | T83: 681 | U83: =IF(OR(T83="",T83>999),$AD$2,T83) -> 681 | V83: 2 | W83: Default | X83: 2022-03-17 | Y83: =IF(ISNUMBER(X83), X83, DATEVALUE(X83)) -> 44637 | Z83: 0.0341
A84: LN-00718 | B84: =IF(A84="", "MISSING", "OK") -> OK | C84: Christine Adams | D84: 52 | E84: =IF(OR(D84<18, D84>100),AD83,D84) -> 52 | F84: Female | G84: =IF(F84="", "Unknown", IF(OR(F84="F", F84="FEMALE", F84="Female"), "Female", IF(OR(F84="M", F84="MALE", F84="Male"), "Male", "Other"))) -> Female | H84: Machakos | I84: Business Owner | K84: =IF(I84="", "Unknown", I84) -> Business Owner | L84: 15 | M84: 1208494 | N84: =IF(OR(M84="",M84<0),$AD$3,M84) -> 1208494 | O84: 634553 | P84: 27.42 | Q84: 36 | R84: Education | S84: =IF(R84="", "Unknown", R84) -> Education | T84: 602 | U84: =IF(OR(T84="",T84>999),$AD$2,T84) -> 602 | V84: 3 | W84: Default | X84: 2021-01-07 | Y84: =IF(ISNUMBER(X84), X84, DATEVALUE(X84)) -> 44203 | Z84: 0.5251
A85: LN-00781 | B85: =IF(A85="", "MISSING", "OK") -> OK | C85: Gregory Lynch | D85: 24 | E85: =IF(OR(D85<18, D85>100),AD84,D85) -> 24 | F85: Female | G85: =IF(F85="", "Unknown", IF(OR(F85="F", F85="FEMALE", F85="Female"), "Female", IF(OR(F85="M", F85="MALE", F85="Male"), "Male", "Other"))) -> Female | H85: Thika | I85: Business Owner | K85: =IF(I85="", "Unknown", I85) -> Business Owner | L85: 8 | M85: 1046183 | N85: =IF(OR(M85="",M85<0),$AD$3,M85) -> 1046183 | O85: 726291 | P85: 24.78 | Q85: 48 | R85: Medical | S85: =IF(R85="", "Unknown", R85) -> Medical | T85: 457 | U85: =IF(OR(T85="",T85>999),$AD$2,T85) -> 457 | V85: 6 | W85: Late (61-90 days) | X85: 2021-09-09 | Y85: =IF(ISNUMBER(X85), X85, DATEVALUE(X85)) -> 44448 | Z85: 0.6942
A86: LN-01334 | B86: =IF(A86="", "MISSING", "OK") -> OK | C86: Jared Giles | D86: 32 | E86: =IF(OR(D86<18, D86>100),AD85,D86) -> 32 | F86: Female | G86: =IF(F86="", "Unknown", IF(OR(F86="F", F86="FEMALE", F86="Female"), "Female", IF(OR(F86="M", F86="MALE", F86="Male"), "Male", "Other"))) -> Female | H86: Machakos | I86: Self-Employed | K86: =IF(I86="", "Unknown", I86) -> Self-Employed | L86: 1 | N86: =IF(OR(M86="",M86<0),$AD$3,M86) -> 1333224 | O86: 400714 | P86: 16.48 | Q86: 48 | R86: Home Improvement | S86: =IF(R86="", "Unknown", R86) -> Home Improvement | T86: 772 | U86: =IF(OR(T86="",T86>999),$AD$2,T86) -> 772 | V86: 0 | W86: Default | X86: 2023-01-09 | Y86: =IF(ISNUMBER(X86), X86, DATEVALUE(X86)) -> 44935 | Z86: 0.2469
A87: LN-01468 | B87: =IF(A87="", "MISSING", "OK") -> OK | C87: Kyle Anderson | D87: 54 | E87: =IF(OR(D87<18, D87>100),AD86,D87) -> 54 | F87: Male | G87: =IF(F87="", "Unknown", IF(OR(F87="F", F87="FEMALE", F87="Female"), "Female", IF(OR(F87="M", F87="MALE", F87="Male"), "Male", "Other"))) -> Male | H87: Meru | I87: Self-Employed | K87: =IF(I87="", "Unknown", I87) -> Self-Employed | L87: 12 | M87: 1117635 | N87: =IF(OR(M87="",M87<0),$AD$3,M87) -> 1117635 | O87: 121407 | P87: 22.74 | Q87: 24 | R87: Medical | S87: =IF(R87="", "Unknown", R87) -> Medical | T87: 1200 | U87: =IF(OR(T87="",T87>999),$AD$2,T87) -> 556 | V87: 5 | W87: Late (61-90 days) | X87: 2022-01-03 | Y87: =IF(ISNUMBER(X87), X87, DATEVALUE(X87)) -> 44564 | Z87: 0.1086
A88: LN-01173 | B88: =IF(A88="", "MISSING", "OK") -> OK | C88: Douglas Wells | D88: 49 | E88: =IF(OR(D88<18, D88>100),AD87,D88) -> 49 | F88: Female | G88: =IF(F88="", "Unknown", IF(OR(F88="F", F88="FEMALE", F88="Female"), "Female", IF(OR(F88="M", F88="MALE", F88="Male"), "Male", "Other"))) -> Female | H88: Nyeri | I88: Business Owner | K88: =IF(I88="", "Unknown", I88) -> Business Owner | L88: 15 | M88: 1700943 | N88: =IF(OR(M88="",M88<0),$AD$3,M88) -> 1700943 | O88: 609421 | P88: 14.91 | Q88: 36 | R88: Education | S88: =IF(R88="", "Unknown", R88) -> Education | T88: 771 | U88: =IF(OR(T88="",T88>999),$AD$2,T88) -> 771 | V88: 2 | W88: Current | X88: 2022-08-26 | Y88: =IF(ISNUMBER(X88), X88, DATEVALUE(X88)) -> 44799 | Z88: 0.3583
A89: LN-00383 | B89: =IF(A89="", "MISSING", "OK") -> OK | C89: Alec Richardson | D89: 42 | E89: =IF(OR(D89<18, D89>100),AD88,D89) -> 42 | F89: Male | G89: =IF(F89="", "Unknown", IF(OR(F89="F", F89="FEMALE", F89="Female"), "Female", IF(OR(F89="M", F89="MALE", F89="Male"), "Male", "Other"))) -> Male | H89: Nakuru | I89: Self-Employed | K89: =IF(I89="", "Unknown", I89) -> Self-Employed | L89: 23 | M89: 259973 | N89: =IF(OR(M89="",M89<0),$AD$3,M89) -> 259973 | O89: 410642 | P89: 16.52 | Q89: 24 | R89: Business | S89: =IF(R89="", "Unknown", R89) -> Business | T89: 440 | U89: =IF(OR(T89="",T89>999),$AD$2,T89) -> 440 | V89: 2 | W89: Late (61-90 days) | X89: 2020-11-19 | Y89: =IF(ISNUMBER(X89), X89, DATEVALUE(X89)) -> 44154 | Z89: 1.5796
A90: LN-00719 | B90: =IF(A90="", "MISSING", "OK") -> OK | C90: Steven Peters | D90: 54 | E90: =IF(OR(D90<18, D90>100),AD89,D90) -> 54 | F90: Female | G90: =IF(F90="", "Unknown", IF(OR(F90="F", F90="FEMALE", F90="Female"), "Female", IF(OR(F90="M", F90="MALE", F90="Male"), "Male", "Other"))) -> Female | H90: Eldoret | I90: Self-Employed | K90: =IF(I90="", "Unknown", I90) -> Self-Employed | L90: 2 | M90: 1201318 | N90: =IF(OR(M90="",M90<0),$AD$3,M90) -> 1201318 | O90: 542154 | P90: 11.54 | Q90: 60 | R90: Personal | S90: =IF(R90="", "Unknown", R90) -> Personal | T90: 749 | U90: =IF(OR(T90="",T90>999),$AD$2,T90) -> 749 | V90: 2 | W90: Default | X90: 2020-04-12 | Y90: =IF(ISNUMBER(X90), X90, DATEVALUE(X90)) -> 43933 | Z90: 0.4513
A91: LN-00208 | B91: =IF(A91="", "MISSING", "OK") -> OK | C91: Michael Mcdonald | D91: 52 | E91: =IF(OR(D91<18, D91>100),AD90,D91) -> 52 | F91: Male | G91: =IF(F91="", "Unknown", IF(OR(F91="F", F91="FEMALE", F91="Female"), "Female", IF(OR(F91="M", F91="MALE", F91="Male"), "Male", "Other"))) -> Male | H91: Eldoret | I91: Business Owner | K91: =IF(I91="", "Unknown", I91) -> Business Owner | L91: 14 | N91: =IF(OR(M91="",M91<0),$AD$3,M91) -> 1333224 | O91: 419371 | P91: 13.19 | Q91: 48 | S91: =IF(R91="", "Unknown", R91) -> Unknown | T91: 457 | U91: =IF(OR(T91="",T91>999),$AD$2,T91) -> 457 | V91: 2 | W91: Charged Off | X91: 2023-01-09 | Y91: =IF(ISNUMBER(X91), X91, DATEVALUE(X91)) -> 44935 | Z91: 0.2047
A92: LN-01376 | B92: =IF(A92="", "MISSING", "OK") -> OK | C92: Jamie Lucero | D92: 43 | E92: =IF(OR(D92<18, D92>100),AD91,D92) -> 43 | F92: Female | G92: =IF(F92="", "Unknown", IF(OR(F92="F", F92="FEMALE", F92="Female"), "Female", IF(OR(F92="M", F92="MALE", F92="Male"), "Male", "Other"))) -> Female | H92: Thika | I92: Business Owner | K92: =IF(I92="", "Unknown", I92) -> Business Owner | L92: 6 | M92: 1852795 | N92: =IF(OR(M92="",M92<0),$AD$3,M92) -> 1852795 | O92: 25750 | P92: 18.5 | Q92: 36 | R92: Agriculture | S92: =IF(R92="", "Unknown", R92) -> Agriculture | T92: 726 | U92: =IF(OR(T92="",T92>999),$AD$2,T92) -> 726 | V92: 7 | W92: Charged Off | X92: 2021-11-02 | Y92: =IF(ISNUMBER(X92), X92, DATEVALUE(X92)) -> 44502 | Z92: 0.0139
A93: LN-00157 | B93: =IF(A93="", "MISSING", "OK") -> OK | C93: Nicole Sherman | D93: 62 | E93: =IF(OR(D93<18, D93>100),AD92,D93) -> 62 | F93: Female | G93: =IF(F93="", "Unknown", IF(OR(F93="F", F93="FEMALE", F93="Female"), "Female", IF(OR(F93="M", F93="MALE", F93="Male"), "Male", "Other"))) -> Female | H93: Eldoret | I93: Self-Employed | K93: =IF(I93="", "Unknown", I93) -> Self-Employed | L93: 11 | M93: 1139192 | N93: =IF(OR(M93="",M93<0),$AD$3,M93) -> 1139192 | O93: 161365 | P93: 21.82 | Q93: 12 | R93: Personal | S93: =IF(R93="", "Unknown", R93) -> Personal | T93: 631 | U93: =IF(OR(T93="",T93>999),$AD$2,T93) -> 631 | V93: 0 | W93: Charged Off | X93: 2021-11-27 | Y93: =IF(ISNUMBER(X93), X93, DATEVALUE(X93)) -> 44527 | Z93: 0.1416
A94: LN-00649 | B94: =IF(A94="", "MISSING", "OK") -> OK | C94: Jeffrey Brown | D94: 48 | E94: =IF(OR(D94<18, D94>100),AD93,D94) -> 48 | F94: Male | G94: =IF(F94="", "Unknown", IF(OR(F94="F", F94="FEMALE", F94="Female"), "Female", IF(OR(F94="M", F94="MALE", F94="Male"), "Male", "Other"))) -> Male | H94: Meru | I94: Self-Employed | K94: =IF(I94="", "Unknown", I94) -> Self-Employed | L94: 19 | M94: 1421597 | N94: =IF(OR(M94="",M94<0),$AD$3,M94) -> 1421597 | O94: 772922 | P94: 26.69 | Q94: 36 | R94: Personal | S94: =IF(R94="", "Unknown", R94) -> Personal | T94: 437 | U94: =IF(OR(T94="",T94>999),$AD$2,T94) -> 437 | V94: 5 | W94: Current | X94: 2020-06-07 | Y94: =IF(ISNUMBER(X94), X94, DATEVALUE(X94)) -> 43989 | Z94: 0.5437
A95: LN-01249 | B95: =IF(A95="", "MISSING", "OK") -> OK | C95: Kristin Schmidt | D95: 46 | E95: =IF(OR(D95<18, D95>100),AD94,D95) -> 46 | F95: Female | G95: =IF(F95="", "Unknown", IF(OR(F95="F", F95="FEMALE", F95="Female"), "Female", IF(OR(F95="M", F95="MALE", F95="Male"), "Male", "Other"))) -> Female | H95: Nyeri | I95: Self-Employed | K95: =IF(I95="", "Unknown", I95) -> Self-Employed | L95: 23 | M95: 2255915 | N95: =IF(OR(M95="",M95<0),$AD$3,M95) -> 2255915 | O95: 719746 | P95: 15.84 | Q95: 60 | R95: Medical | S95: =IF(R95="", "Unknown", R95) -> Medical | T95: 566 | U95: =IF(OR(T95="",T95>999),$AD$2,T95) -> 566 | V95: 1 | W95: Default | X95: 2023-06-02 | Y95: =IF(ISNUMBER(X95), X95, DATEVALUE(X95)) -> 45079 | Z95: 0.319
A96: LN-00922 | B96: =IF(A96="", "MISSING", "OK") -> OK | C96: Mark Torres | D96: 57 | E96: =IF(OR(D96<18, D96>100),AD95,D96) -> 57 | F96: Male | G96: =IF(F96="", "Unknown", IF(OR(F96="F", F96="FEMALE", F96="Female"), "Female", IF(OR(F96="M", F96="MALE", F96="Male"), "Male", "Other"))) -> Male | H96: Nairobi | I96: Self-Employed | K96: =IF(I96="", "Unknown", I96) -> Self-Employed | L96: 11 | M96: 666799 | N96: =IF(OR(M96="",M96<0),$AD$3,M96) -> 666799 | O96: 37413 | P96: 11.93 | Q96: 60 | R96: Medical | S96: =IF(R96="", "Unknown", R96) -> Medical | T96: 577 | U96: =IF(OR(T96="",T96>999),$AD$2,T96) -> 577 | V96: 1 | W96: Late (61-90 days) | X96: 08-05-2021 | Y96: =IF(ISNUMBER(X96), X96, DATEVALUE(X96)) -> 44413 | Z96: 0.0561
A97: LN-00505 | B97: =IF(A97="", "MISSING", "OK") -> OK | C97: Tracy Alvarez | D97: 56 | E97: =IF(OR(D97<18, D97>100),AD96,D97) -> 56 | F97: Male | G97: =IF(F97="", "Unknown", IF(OR(F97="F", F97="FEMALE", F97="Female"), "Female", IF(OR(F97="M", F97="MALE", F97="Male"), "Male", "Other"))) -> Male | H97: Kisumu | I97: Business Owner | K97: =IF(I97="", "Unknown", I97) -> Business Owner | L97: 0 | M97: 583322 | N97: =IF(OR(M97="",M97<0),$AD$3,M97) -> 583322 | O97: 760389 | P97: 16.53 | Q97: 60 | R97: Education | S97: =IF(R97="", "Unknown", R97) -> Education | T97: 692 | U97: =IF(OR(T97="",T97>999),$AD$2,T97) -> 692 | V97: 0 | W97: Late (31-60 days) | X97: 2020-03-19 | Y97: =IF(ISNUMBER(X97), X97, DATEVALUE(X97)) -> 43909 | Z97: 1.3035
A98: LN-00311 | B98: =IF(A98="", "MISSING", "OK") -> OK | C98: Kathy Garcia | D98: 50 | E98: =IF(OR(D98<18, D98>100),AD97,D98) -> 50 | F98: Male | G98: =IF(F98="", "Unknown", IF(OR(F98="F", F98="FEMALE", F98="Female"), "Female", IF(OR(F98="M", F98="MALE", F98="Male"), "Male", "Other"))) -> Male | H98: Nyeri | I98: Employed | K98: =IF(I98="", "Unknown", I98) -> Employed | L98: 29 | M98: 574274 | N98: =IF(OR(M98="",M98<0),$AD$3,M98) -> 574274 | O98: 785419 | P98: 14.17 | Q98: 12 | R98: Medical | S98: =IF(R98="", "Unknown", R98) -> Medical | T98: 799 | U98: =IF(OR(T98="",T98>999),$AD$2,T98) -> 799 | V98: 7 | W98: Default | X98: 2023-09-17 | Y98: =IF(ISNUMBER(X98), X98, DATEVALUE(X98)) -> 45186 | Z98: 1.3677
A99: LN-01396 | B99: =IF(A99="", "MISSING", "OK") -> OK | C99: Meagan Calderon MD | D99: 60 | E99: =IF(OR(D99<18, D99>100),AD98,D99) -> 60 | F99: Female | G99: =IF(F99="", "Unknown", IF(OR(F99="F", F99="FEMALE", F99="Female"), "Female", IF(OR(F99="M", F99="MALE", F99="Male"), "Male", "Other"))) -> Female | H99: Nakuru | I99: Employed | K99: =IF(I99="", "Unknown", I99) -> Employed | L99: 0 | M99: 1360788 | N99: =IF(OR(M99="",M99<0),$AD$3,M99) -> 1360788 | O99: 65619 | P99: 14.83 | Q99: 12 | R99: Home Improvement | S99: =IF(R99="", "Unknown", R99) -> Home Improvement | T99: 737 | U99: =IF(OR(T99="",T99>999),$AD$2,T99) -> 737 | V99: 4 | W99: Fully Paid | X99: 2023-01-05 | Y99: =IF(ISNUMBER(X99), X99, DATEVALUE(X99)) -> 44931 | Z99: 0.0482
A100: LN-00959 | B100: =IF(A100="", "MISSING", "OK") -> OK | C100: Justin Brooks | D100: 55 | E100: =IF(OR(D100<18, D100>100),AD99,D100) -> 55 | F100: Female | G100: =IF(F100="", "Unknown", IF(OR(F100="F", F100="FEMALE", F100="Female"), "Female", IF(OR(F100="M", F100="MALE", F100="Male"), "Male", "Other"))) -> Female | H100: Kakamega | I100: Unemployed | K100: =IF(I100="", "Unknown", I100) -> Unemployed | L100: 15 | M100: 271006 | N100: =IF(OR(M100="",M100<0),$AD$3,M100) -> 271006 | O100: 389360 | P100: 19.29 | Q100: 24 | R100: Agriculture | S100: =IF(R100="", "Unknown", R100) -> Agriculture | T100: 312 | U100: =IF(OR(T100="",T100>999),$AD$2,T100) -> 312 | V100: 2 | W100: Late (31-60 days) | X100: 2022-05-28 | Y100: =IF(ISNUMBER(X100), X100, DATEVALUE(X100)) -> 44709 | Z100: 1.4367
...

Sheet Data_Quality_Doc
A1: Data Quality Issues | B1: Number of Records | C1: Action Taken When Cleaning | D1: Reason
A2: Blank Loan_IDs | B2: =COUNTBLANK(Loan_Data!A2:A1517) -> 10 | C2: Delete all 10 rows | D2: LOAN ID is the primary key. Without it, records can't be ID'd, linked, or tracked
A3: Abnormal Ages(<18, >100) | B3: =COUNTIFS(Loan_Data!C2:C1517, "<18") + COUNTIFS(Loan_Data!C2:C1517, ">100") -> 10 | C3: Replaced with median age(44) | D3: Median is resistant to that distortion and gives you the "typical" borrower age
A4: Negative Annual Incomes | B4: =COUNTIF(Loan_Data!H2:H1517, "<0") -> 14 | C4: Replaced with median annual income | D4: Income cannot be negative. Treated it as an error.
A5: Inconsistent Casings(Gender) | B5: F, FEMALE, Female, M, Male | C5: Standardised casing to Male/Female | D5: Helps when it comes to gender analysis
A6: Blank Gender | B6: =COUNTBLANK(Loan_Data!D2:D1517) -> 38 | C6: Added Other to gender - maybe didn't want to disclose gender
A7: Blank Employment Status | B7: =COUNTBLANK(Loan_Data!F2:F1517) -> 31 | C7: Added Unknown to blank ones | D7: Employment status/income directly affects creditworthiness assessment and wrong imputation would distort analysis
A8: Blank Annual Income | B8: =COUNTBLANK(Loan_Data!H2:H1517) -> 49 | C8: Replaced with calculated median annual income
A9: Blank Loan Purpose | B9: =COUNTBLANK(Loan_Data!L2:L1517) -> 58 | C9: Replaced with unknown
A10: Blank Credit Score | B10: =COUNTBLANK(Loan_Data!M2:M1517) -> 55 | C10: Replaced with calculated median credit score
A11: Mixed Date Formats | B11: YYYY-MM-DD | C11: Formated column as a date, chose YYYY-MM-DD | D11: Compatible with most databases
B12: MM-DD-YYYY
B13: DD MON YYYY
